Workbook

Sheet Raw_data
A1: User_Id | B1: Product_ID | C1: user | D1: Date/ timestamp | E1: title | F1: extension | G1: is_helpful | H1: rating | I1: review | J1: category
A2: AH5M24Z73ZHQGN77WA3JT3Q7TEBQ | B2: PROD001 | C2: Clara | D2: 45658.158 | E2: NUWAVE, GRILL IS PRETTY GOOD SO FAR | F2: Verified Purchase | G2: 87 | H2: 5 | I2: This is a pretty good little grilling cookerIt's easy to use and clean, and with a bunch of time and temperature settings you can easily air grill all kinds of meat | J2: kitchen
A3: AFI7ALURI5CPDT4V7CUXZXLNFDVA | B3: PROD002 | C3: Wyeventer | D3: 45658.222 | E3: Game changer | F3: Verified Purchase | G3: 119 | H3: 5 | I3: I wasn't sure I needed an air fryer. I'm so glad I took the leap! | J3: kitchen
A4: AENH6LSB6BM7XLPEYUL43WBOD6JA | B4: PROD003 | C4: A | D4: 45658.447 | E4: More Than Meets My Needs | F4: Verified Purchase | G4: 87 | H4: 4 | I4: My Needs:Smallish footprint.No burns.Even cooking.Versatility.Intuitive operation or a good manual.Durability.Shouldn't be too hard, right? I had an Emerson convection toaster oven that took great care of my family for almost exactly 15 years. When it died a week ago, I looked at the counter space and thought SCORE!Then we tried to live without a toaster oven.I have a Samsung smart range that I would marry if not for my husband's objections. It does a lot and has a lot of perfectly calibrated presets. But it's a big machine that uses gas and electricity and takes a while to heat up and that's a lot to reheat a slice or a sandwich. And, even though it's a lot better insulated than the oven it replaces, it does heat the kitchen in the summer.And wouldn't you know it? Right after the toaster oven died, we had need to heat a sandwich. The dead toaster oven was oppressing us.It's a first world problem and we are first world people, but we are not made of money, and it was Presidents Day. So we bought this thing.It stays cool enough to be able to put your hand on it while it airfries. My actual air fryer will scorch you if you try laying hands on it. You can touch the sides, the top, the door, the handle. Warm? Yes. Do you harm? No.The footprint is smaller than my old one. It's small enough that I can pull it out to the end of the counter and not have it under my cabinets while it cooks.So far, it cooks perfectly evenly. Tater tots come out looking like little brown shirts or army tots, completely conforming, each to the others. The probe seems accurate.Accessories were easy to set up, but the oven operation is a bit opaque on the panel. Luckily, the manual works. It's an alleged air fryer? But there's no preset for that (you can make one if you're into operator's manual deep dives).And it's very versatile - bread proof/yogurt temp all the way up to air fry. I just lost the need for three different appliances.Hope this thing lasts. I kind of love it. | J4: kitchen
A5: AHFAAT5CJ6IIGIURHFBICP44ZHVA | B5: PROD004 | C5: Aylene W. Barr | D5: 45658.657 | E5: Great machine and incredible customer support! | F5: Verified Purchase | G5: One | H5: 5 | I5: My family is following a low carb diet and we have essentially six adults living together (MIL and adult children still here while going to college etc) so there is food being cooked at all hours of the day. This machine is used at least twice a day, sometimes five or six times a day. Crisy bacon is easy, frozen patties cooked to done and great for chicken nuggets too.We were very unhappy when I started getting an error message when preheating and worried that it might be dangerous. I looked up the online customer manual and found the error message listed there. I followed the directions and emailed customer service for help. I received a response on the same day and they sent me a replacement unit free of charge that I got in less than a week. The box includes a return shipping sticker (prepaid) to send back the defective unit. That is customer service!The new unit works great and we are back in business! | J5: kitchen
A6: AG4UMTWF2QN3BRDCSNVXTGZTPCAA | B6: PROD005 | C6: Ivette | D6: 45658.837 | E6: Love it | F6: Verified Purchase | G6: One | H6: 5 | I6: I bought this nuwave brio in November 2020. I never did a review but I want to do it know. In Nov 2025 will be 5 years using this airfryer and I can't live with out her. Perfection cooker in food, perfect rotisserie chicken, juicy red meat. The numbers in panel are intact and perfect size for my kitchen. | J6: kitchen
A7: AHO5TWX2UUDF22I2XOW4SZN2GDRQ | B7: PROD006 | C7: Djinn | D7: 45658.996 | E7: Works great! | F7: Verified Purchase | H7: 5 | I7: I love the design as well as the ease and of using it. | J7: kitchen
A8: AFKZUIF6G6FKXDFO22NL5W3ZLHUQ | B8: PROD007 | C8: Ethan | D8: 45659.039 | E8: Quiet! Hot! It has Rotisserie!! | F8: Verified Purchase | G8: 28 | H8: 5 | I8: Ok. I almost NEVER write Product reviews, but this Air Fryer absolutely blew me away (pun intended).First things first, the sound. One of the things that made me want to spend a bit more on an Air fryer than I did initially (this is my second fryer in the past few years) is the noise. My first Air fryer (about $70) was LOUD and it got annoying as I work in the room next to it. This thing comparatively makes almost no noise.Next, my favorite feature, Rotisserie. I never thought I needed this feature until I tried it. It does a REALLY good job. I am able to rotisserie two chicken breasts at the same time quite comfortably using the included basket. The chicken comes out after about 18 minutes hot, crispy and juicy!I have also done a fair amount of "bulk cooking" making an entire dinner across 3 racks for a family of 5 fairly comfortably.I haven't used the included probe yet, but having the ability to cook to temperature is exciting.Finally, the most hidden gem feature is easily the glass front and light. I can watch my food cook! Very often I am cooking something I haven't air fried before, so I don't know exactly how long I would need, and being able to watch it cook and make decisions based on what I am seeing is a game changer! | J8: kitchen
A9: AF44IYYKVBHBUNKQEICMO4T7MJ6Q | B9: PROD008 | C9: Benjamin Solheim | D9: 45659.26 | E9: Good for cheese burgers | F9: Verified Purchase | G9: One | H9: 5 | I9: I had trouble getting it to cook perogies, they either are too hard or undercooked. But cheese burgers at 350 for 4 minutes on a side for normal size patty came out a nice medium. It is a pita to clean even with the removable drip tray but not needing to use my over is nice. I've made a couple things in it I found the temps and times from youtube videos mostly. Some things are faster some things are slower but most things are similar times to a regular over. | J9: kitchen
A10: AGTVNHEOZCRUASEIU2QX6JBVWNCQ | B10: PROD009 | C10: jackie hodges | D10: 45659.377 | E10: oven | F10: Verified Purchase | H10: 5 | I10: this was a great addition to my kitchen. But it was to large for the space that i have. So I returned it | J10: kitchen
A11: AEZMHCTOR4XWPQJJEP47UBY2G4UA | B11: PROD010 | C11: gabriel | D11: 45660.153 | E11: Good | F11: Verified Purchase | H11: 4 | I11: Goog | J11: kitchen
A12: AFGOHTTJWRAYHJQKZZULDJID5ADQ | B12: PROD011 | C12: Yuki | D12: 45660.29 | E12: Great tool for busy mom | F12: Verified Purchase | G12: 48 | H12: 5 | I12: First time Apple Watch user and I am very happy with the purchase. As a mom of toddler, this is very helpful tool so that I get notification while my phone is inside stroller or diaper bag and chasing my child in the park. I also love the GPS and emergency notification that I can share with my family. I have started to work out little more and care for health as it encourage to stand up, track movement etc which is very helpful. Iâ€™m impressed with the battery life and how fast it charges too! Iâ€™ve been using iPhone since it came out and MacBook but Apple Watch was something I didnâ€™t think I needed. Itâ€™s not something you need, but it is well worth investing to make your life easier. Watch quality and size is perfect for my arm and it is durable and water resistance so I donâ€™t have to worry about it while playing in the splash pad or parks too! | J12: Electronics
A13: AFFUJJPQEWVDXYGSKC3SLMIIU75Q | B13: PROD012 | C13: Saby | D13: 45660.524 | E13: Amazing, my favorite purchase | F13: Verified Purchase | G13: 2 | H13: 5 | I13: Absolutely love this watch! Itâ€™s my first smart watch, so I decided to start with the SE and if I wanted to upgrade to the Series 9/10 I could later. But this little watch does everything I need it to. I donâ€™t work out a lot, but I enjoy using it when I dance and go on walks. I like that you can text or answer calls quickly when youâ€™re away from your phone. I have a very hands-on job, but the screen looks good, some scratches if you look reallly hard, but no large cracks. I also really like the starlight color, itâ€™s a nice warmer silver that matches more of my outfits/jewelry. Vernal, very happy with it. | J13: Electronics
A14: AEWQC7JKO4RBKIHOK3U7S7PJ5O6A | B14: PROD013 | C14: Shelby | D14: 45660.793 | E14: Daily watch | F14: Verified Purchase | G14: 3 | H14: 5 | I14: I bought this watch over a year ago and I do love it. It tracks my activity, I can talk on the phone, text back, it will even find my phone if I lose it! The battery tends to die fairly quick. I have to charge it once a day. The color is pretty and is a very durable watch. All in all, I highly recommend the Apple Watch! | J14: Electronics
A15: AHJGHJOHYP5YGMOACP4BNXQKZTIQ | B15: PROD014 | C15: Sunny dhama | D15: 45661.038 | E15: Great battery life and seamless integration! | F15: Verified Purchase | G15: 96 | H15: 5 | I15: I recently acquired the Apple Watch SE (2nd Gen) with the Starlight Aluminum Case and Starlight Sport Band, and I must say it has been a game-changer for me. As a graduate student pursuing a master's in computer science at the University of Florida and a research assistant at the Learn Dialogue Lab, I needed a smartwatch that could seamlessly integrate into my active lifestyle, help me stay on top of my health, and even assist in my research tasks. The Apple Watch SE has exceeded my expectations in all these aspects.One of the standout features for me is the fitness and sleep tracking capabilities. With my busy schedule, it's crucial to keep tabs on my physical activity and sleep patterns. The Apple Watch SE does an excellent job of tracking my steps, calories burned, and even encourages me to move when I've been sitting for too long. The sleep tracking feature has been a revelation, providing insights into the quality of my sleep and helping me make adjustments for better rest.Being a tech enthusiast and someone deeply involved in the IT sector, I appreciate the crash detection and heart rate monitoring functions. Safety is paramount, and the watch's ability to detect a potential fall and initiate an emergency call is a reassuring feature, especially when I'm out traveling or in the middle of a research project. The heart rate monitor keeps me informed about my cardiovascular health during workouts and daily activities.As someone who loves teaching and mentoring, the Apple Watch SE also helps me manage my busy schedule. The calendar notifications and reminders keep me on track for meetings with my mentees and colleagues at the lab, which is essential for our collaborative projects, such as "Collaborative sports," "Amby: Language model for middle schoolers," and "Integrate AI."Moreover, the watch seamlessly integrates with my iPhone, allowing me to respond to messages, emails, and calls without taking out my phone, which is incredibly convenient during our frequent lab meetings and while I'm on the go.In conclusion, the Apple Watch SE (2nd Gen) has become an indispensable part of my daily life. Its fitness and health-tracking features, coupled with its integration into my professional and academic activities, make it a must-have for anyone in the IT sector aiming to be a leader in future IT solutions. Whether I'm teaching React JS or exploring new states in the USA, this smartwatch has proven to be a reliable companion. Highly recommended! | J15: Electronics
A16: AEEEIOCKG5TKBOHMHNLSAGAQRHZQ | B16: PROD015 | C16: M@reBe@r | D16: 45661.145 | E16: Best watch for iOS users, itâ€™s a no-brainer! | F16: Verified Purchase | G16: 39 | H16: 5 | I16: I was always a Fitbit user for my iPhone because I thought Apple Watch was too pricey for me. I started out with the Fitbit Blaze which was fine then upgraded to the first Sense watch which was junk. It finally died on me after only 3 years and the glue didnâ€™t hold up so the face popped off. So I was in the market for a new smart watch.Finally broke down and bought this watch. Price for the SE was similar to the Fitbit.This is night and day!! If youâ€™re on the fence about which one to choose, go with the Apple Watch!!The only downside is you have to charge it daily. Youâ€™ll get used to it. Itâ€™s fine, youâ€™ll live.Itâ€™s beautiful, stylish but most of all you get all the features that mimics your phone. Youâ€™re not limited to the basics like you are with Fitbit. With the Apple Watch you can do it all so you get more bang for your buck. Donâ€™t think on it. Just get this. Itâ€™s a no-brainer. Woot! | J16: Electronics
A17: AE3JRWFDK7YKPRU5LQVQSJQWGB7A | B17: PROD016 | C17: JosÃ© A. Corleto | D17: 45661.618 | E17: Nice and affordable watch | F17: Verified Purchase | H17: 4 | I17: I bought it for my wife and sheâ€™s happy with it.As many other customers say, the battery life is not the best. It can barely last for around 18 hours despite most of the background processes are turned off. | J17: Electronics
A18: AECKACZU66B2I754RUINZDECF3AQ | B18: PROD017 | C18: Tyandra PTyandra P | D18: 45661.65 | E18: Authentic product | F18: Verified Purchase | G18: 2 | H18: 5 | I18: Iâ€™ve had it for a few months now and itâ€™s easy to set up, affordable and very convenient for me when iâ€™m at work. I love the color and size of it tooâ˜ºï¸ | J18: Electronics
A19: AHKYMAJBD6UHJMES64ZTISYKNM5A | B19: PROD018 | C19: Ricardo | D19: 45661.755 | E19: Great apple watch | F19: Verified Purchase | H19: 5 | I19: Bought this for my sister after we bough a used one that barely worked. This works perfect and my sister absolutely loves it. We got it for her birthday and she says it fits her perfect and works amazing. She said the battery life is great and it charges fine. My sister does manual labor and said the watch has taken a beating but doing really good. She loves it so much and it is a great product. I have grown fond of apple but still they need to work on some things haha. | J19: Electronics
A20: AEX3T6BZUU3X7SW3NVMRRB26BYDQ | B20: PROD019 | C20: aleciaalecia | D20: 45661.942 | E20: Great Watch | F20: Verified Purchase | H20: 5 | I20: I bought this watch for my daughter & she loves it. It has alot of great features and works well with her Iphone. It's very user-friendly & the apps are easy to navigate. The battery works efficiently and last for a long time. | J20: Electronics
A21: AEK55BORHMM5XESWCDLS3TAFSEHQ | B21: PROD020 | C21: Marie | D21: 45662.459 | E21: Apple Watch/fitness tracker | F21: Verified Purchase | H21: 5 | I21: I have had this watch for over a year super functional quality to watch is amazing. Very durable. I work out with all my wrist every day and donâ€™t even know itâ€™s on my wrist. Due to how itâ€™s very lightweight and it charges super quick at night itâ€™s charged within probably an hour. | J21: Electronics
A22: AE563QU2VOUFPWLJ266B6DHQJT5Q | B22: PROD021 | C22: Tiffany Lee Mezo | D22: 45662.763 | E22: Watch Saver | F22: Verified Purchase | H22: 5 | I22: Well, my mom was out for a walk when she fell and the watch actually called 911! I didnâ€™t know it would do this! EMS came and cleaned her wounds up. That God for this watch!!!! | J22: Electronics
A23: AEHRQQWGO6WRJNDGCXC5EUG6TNGQ | B23: PROD022 | C23: Karla | D23: 45662.914 | E23: I purchased a watch front & back cover to keep it nicer. | F23: Verified Purchase | H23: 5 | I23: Iâ€™m liking that I can change my watch bands. My other Apple Watch I couldâ€™t get the watch band on one side the button would not push in no how no way. I could actually set the watch up to my phone myself! | J23: Electronics
A24: AGAYKCP2GM6DDHHJLW6CTBWKBSMA | B24: PROD023 | C24: Tasha | D24: 45663.311 | E24: Apple Watch accessories | F24: Verified Purchase | H24: 5 | I24: Color is nice and great fit | J24: Electronics
A25: AFCZNLXHN2L3OFOETOBGK42LBBEQ | B25: PROD024 | C25: BLJL25BLJL25 | D25: 45663.495 | E25: Perfect | F25: Verified Purchase | H25: 5 | I25: Got this on sale and itâ€™s perfect. My old watch broke and was so bummed until I found this perfect replacement | J25: Electronics
A26: AEICPXK6OTUMCQPNXNOZ5MU2NXEA | B26: PROD025 | C26: ElizabethElizabeth | D26: 45663.731 | E26: It wakes me up in the morning by tapping my wrist, without waking up anyone else | F26: Verified Purchase | G26: One | H26: 5 | I26: My last watch the glass kind of chipped and started breaking so I figured to get a new watch.I think I went down as far as what features the Watch can do to this SE watch. But it still has the functions that I actually want. For example, it wakes me up when the alarm goes off; that way, it doesnâ€™t wake up anyone else because itâ€™s not beeping. Itâ€™s just tapping my wrist.I can also use the other functions that has such as answering the phone and answering texts. You can also check the weather and you can see the pictures that people sent you.There are really so many features to it that Iâ€™m not really sure that I would need the watch that has more features because this is really a good watch!I highly recommend this watch. Itâ€™s really good and it looks nice and the feature where it wakes me up without having to go off, but just tap my wrist, is the reason I actually bought this watch.I highly recommend this watch! you should get it! | J26: Electronics
A27: AHZMTCAM7PECOL2L7QZVF225VONA | B27: PROD026 | C27: Jae | D27: 45663.96 | E27: Great gift | F27: Verified Purchase | H27: 5 | I27: Got this as a gift and they loved it! Works well and looks very nice! | J27: Electronics
A28: AE4T7OL4UCDBFVWFKPEUCJR5CKKA | B28: PROD027 | C28: Amazon Customer | D28: 45664.697 | E28: you have to charge it everyday | F28: Verified Purchase | H28: 4 | I28: the battery does not last very long. | J28: Electronics
A29: AFVA2N7GIU6SSK2K26QC7JE2CI3A | B29: PROD028 | C29: Darlene Cooley | D29: 45665.528 | E29: Happy with watch | F29: Verified Purchase | H29: 5 | I29: Happy with this watch. Has all the functions I need and use. A charge usually lasts me two days. Would buy again. | J29: Electronics
A30: AHKAY36QG2ZU2ETEC7R26LDSLIHA | B30: PROD029 | C30: Summer G.Summer G. | D30: 45665.564 | E30: Satisfied | F30: Verified Purchase | G30: One | H30: 4 | I30: The media could not be loaded. The only reason I ordered it from Amazon not the official website was because the price was lower. It arrived in a perfect condition. As for the product, Iâ€™m satisfied with it just like any other Apple products. Iâ€™ve had it for a month but I donâ€™t wear it all day just because I donâ€™t like having anything on my wrist. Itâ€™s mostly for workout purposes. The only thing I donâ€™t approve of is the battery life. The battery runs out fast even when I leave it on a counter all day. But like I said, since I donâ€™t wear it often. It doesnâ€™t bother me too much. | J30: Electronics
A31: AH524CD5S6DI4M665QORBS6QJL3Q | B31: PROD030 | C31: Fattiesmama | D31: 45665.585 | E31: Exactly what we wanted | F31: Verified Purchase | H31: 5 | I31: Ordered this watch as a replacement for an old watch. It was everything we needed and arrived in a timely manner. The watch is new and sealed, it paired fine with the phone. | J31: Electronics
A32: AHRQQN36UWBMDXA7G53775PYRJRQ | B32: PROD031 | C32: Matt P. | D32: 45665.915 | E32: My daughter loves it | F32: Verified Purchase | H32: 5 | I32: Bought this for my daughter for Christmas 2023, after her wearing it pretty much everyday for a year it's still going strong and works great. She loves it. | J32: Electronics
A33: AE74NWBRHXSGMN5AWZHDGAZNMBCQ | B33: PROD032 | C33: Amazon Customer | D33: 45666.057 | E33: Love, love, love it | F33: Verified Purchase | H33: 5 | I33: I am so happy with this watch. I should have gotten it sooner. All these years with a phone, I forgot how nice it is to hear have a watch. I love seeing the temperature at a glance, and what my next appointment is. I love the ease of health monitoring, controlling music playback, and receiving messages even if Iâ€™m not near my phone.I donâ€™t care for the band, but there are endless replacement possibilities. I was thrown off by the USBC charger, but itâ€™s no big deal now. I also bought normal-USB-compatible backup chargers for my car and my office. The charging speed is good. I bought a screen protector/cover and itâ€™s already pretty banged up, so Iâ€™m glad I did. | J33: Electronics
A34: AGDJD5B3AUVK4WGEDM2S7YEKB7FA | B34: PROD033 | C34: Amazon Customer | D34: 45666.169 | E34: Okay, I'm a convert | F34: Verified Purchase | H34: 5 | I34: I really loved my Fitbit Luxe for its small size and stylish look. I didn't really need all the extras an Apple watch offers, and I didn't want to wear the big clunky Apple. But when Google took over and my last Fitbit died for the final time. it appeared that it really wasn't being supported any longer. Why did I wait so long? This watch is waaaay more than I really need, but I love it! There are lots of replacement bands available to lessen the utilitarian appearance. | J34: Electronics
A35: AHKETNWF3EFO54W2U2AGW4GGHIOA | B35: PROD034 | C35: Bretz | D35: 45666.52 | E35: Battery life | F35: Verified Purchase | H35: 4 | I35: Itâ€™s a pretty good item, the battery life just doesnâ€™t last as long as Iâ€™d expect. | J35: Electronics
A36: AHG62TLHNV6VMSHX6ZKLKK6GBQCQ | B36: PROD035 | C36: Jan | D36: 45667.19 | E36: It's OK | F36: Verified Purchase | H36: 3 | I36: This watch has some nice features: being able to receive emails and phone calls on it from your iPhone is very convenient, as is the sleep schedule/wind down feature. The wide choice of watch faces that show different information (or none at all if that's what you want) is nice to have.I had a Fitbit Charge 5 (which I opted not to replace when it died bc Fitbit seems to have reliability issues) & some of the features I loved about that watch were that it showed real-time info on your heart rate without having to click off to another screen, and it tracked SPO2 info, which this watch does not & you will have to buy a separate pulse oximeter. You will need to charge this watch every day, as opposed to every 4-5 days with a Fitbit. And the band that came with the watch kept popping off. I ended up buying a set of silicone watchbands from a third-party seller on Amazon that had a rectangular stud instead of a round one & that solved the popping-off problem.I'm still trying to figure out the Activity app on this watch bc i don't find it easy to follow & don't feel that it provides good real-time info on your activity levels, but maybe that's just bc I haven't figured it all out yet.It seems like this watch is really more for people who want the convenience of having a mini-iPhone on their wrist than for people who want to track their health and fitness. | J36: Electronics
A37: AGOEB7I7DMZOWRJH4H2VTGE7AWYQ | B37: PROD036 | C37: SarahSarah | D37: 45667.486 | E37: Easier than going to the store. | F37: Verified Purchase | G37: 23 | H37: 5 | I37: When my original Apple Watch started having problems, I thought I was going to have to go wait in store to buy a new watch but when I found this one on Amazon, I thought it would be too good to be true. This watch is exactly the same as what you would buy in store, but without the wait. I have always liked this Apple Watch because I've never needed the newest one. The functionality, sound quality, Watch quality, and weight were always some of my favorite things about it. I love that this one came with the more cream/rose colored band. But for work I usually just used my old band so I donâ€™t damage the new one. If you want an Apple Watch at a good price and donâ€™t need the newest one, I would suggest this one. I like the price of it a lot better too. | J37: Electronics
A38: AHRLNVY3M6VKWNYR5J6OZGYHHUBA | B38: PROD037 | C38: Sandy | D38: 45667.626 | E38: 1st time Apple Watch wearer! | F38: Verified Purchase | H38: 5 | I38: And I love it! | J38: Electronics
A39: AFCVISYWC2AVDOXPZKNIB6PUHRMQ | B39: PROD038 | C39: Roland Frymire | D39: 45667.713 | E39: Great little watch except for one important thing | F39: Verified Purchase | G39: 5 | H39: 4 | I39: Iâ€™ve owned a couple of these Apple watches that are great products with the exception of one major problem. I have also purchased non-apple watches that cost much less that have had a much longer battery life than the Apple Watch. I donâ€™t understand why the Apple Watch has a pathetic battery life wherein the much cheaper watches are Incredibly proficient in their battery life. The battery life for an Apple Watch is on the average is 24 hours wherein the other much less expensive non-Apple watches can go for days or even weeks. Shame on Apple. | J39: Electronics
A40: AGXQFILAA7LDXARFEIYWDGGBWAFQ | B40: PROD039 | C40: SunDevil03 | D40: 45667.973 | E40: Fiance Loves It | F40: Verified Purchase | G40: One | H40: 5 | I40: My fiance has never had a smart watch and she would often talk about how cool it would be. But she doesn't make a ton of money so it's always been a bit of a pipe dream. Well her birthday came around and this watch was at a great price, so I had to pick it up for her. She absolutely loves it. Perfect functionality. It's not too big, but still big enough to be useful.Personally I'm a Samsung guy and I've got a Galaxy Watch that I love, but she sure loves her Apple Watch and so far it appears to be a big winner. | J40: Electronics
A41: AGPZMNVA52KNZMA2KEIBJ74EUAUA | B41: PROD040 | C41: Robert Gala | D41: 45668.045 | E41: Love it | F41: Verified Purchase | H41: 5 | I41: I wasnâ€™t really a watch guy, or at least I wasnâ€™t until recently. This watch has changed my life. It offers so many features that I canâ€™t even begin to list them all. Iâ€™ve said this before, but itâ€™s truly amazing. If you work out, run errands, use Apple Pay, or just want a convenient way to keep track of your time, this watch is for you. I highly recommend it. You wonâ€™t regret this purchase. | J41: Electronics
A42: AF2G47CBXMAILR36PQ53GPRZRY6Q | B42: PROD041 | C42: PaNhia | D42: 45668.306 | E42: Love it but the battery dies way too fast | F42: Verified Purchase | H42: 4 | I42: I love the product. However, the battery dies way too fast within one day even if Iâ€™m not using it. I would say it lasts me about a good 5-6 hrs. Need to charge it every day. | J42: Electronics
A43: AFZGVAGNQJXZJRWNM4VPPM4HGKTQ | B43: PROD042 | C43: Kimberly Leksen | D43: 45668.473 | E43: Watch | F43: Verified Purchase | H43: 4 | I43: Nice watch however Iâ€™m still trying to figure some things out. I had a Fitbit versa 2 prior to this Apple Watch.Seems like my text messages are not received by my phone. Maybe I need a new iPhone Iâ€™m still using my old 11. And the battery life does dwindle quick. Otherwise itâ€™s a super cute watch and has many options. I did talk on it and was able to answer my phone on the watch and the sound was awesome. ðŸ˜Ž | J43: Electronics
A44: AGMY7JWCQVFJC7XP4TKPIIJBJVEQ | B44: PROD043 | C44: Michelle | D44: 45668.525 | E44: Love Love | F44: Verified Purchase | H44: 5 | I44: Wanted to start out with a cheaper version of the watch to make sure I really like it. And I love it! I use it mostly for fitness and checking important notifications when I don't have my phone nearby. I also love the sleep tracker and the heart rate monitor. I see the other features that come with the other apple watch such as the airfib, which this one doesn't have. But I believe this is a good starter watch for those who may have never owned a smart watch like this. Then in the future you can upgrade if necessary. | J44: Electronics
A45: AEYNIGTERZ2VQJADFPAHMMXFEY6A | B45: PROD044 | C45: J. Dean | D45: 45668.719 | E45: Bought in Prime Days n Worth It | F45: Verified Purchase | H45: 5 | I45: Iâ€™ve been eye balling these watches for awhile. When I saw the pricing on this one during Amazon Prime Days I bought it. No regrets really. I like that it measures how many calories Iâ€™ve burnt at the gym, being able to talk to someone while Iâ€™m busy working without having to hold my phone. It also is an easy reference for checking notifications whether texts or prompts from sources Iâ€™ve chosen. The watch does charge fast as it will lose battery life if worn all day | J45: Electronics
A46: AGTTE5HS7SZFAWMC6P2WLQ5UJVGQ | B46: PROD045 | C46: A. Liegl | D46: 45669.146 | E46: Does the job | F46: Verified Purchase | H46: 4 | I46: Received this watch & has everything I need to monitor my lifestyle. I wish the battery would last longer & didnâ€™t have to charge it so often | J46: Electronics
A47: AHHVQ4GWPNWFAP3YAR6EKGPEOMQQ | B47: PROD046 | C47: Pamela Ott | D47: 45669.212 | E47: Love This Watch | F47: Verified Purchase | H47: 5 | I47: I purchased this watch to replace my series 4. I have really small wrists so the watch was the same size as my series 4. I do like the color of the band but I only wear the original band for a short time because it does get dirty fast. | J47: Electronics
A48: AHS22FERVIN3GXYIIEQMHPYMJZTA | B48: PROD047 | C48: Tsb | D48: 45669.242 | E48: Battery life | F48: Verified Purchase | H48: 4 | I48: Love the watch itself but battery life is less than 24 hrs. Not ideal | J48: Electronics
A49: AEU67U54MXRR5MTKPWM3YAFTTSDQ | B49: PROD048 | C49: ð™¹ð™°ðš‚ð™¼ð™¸ð™½ð™´ ðŸŒ» | D49: 45669.272 | E49: Perfect and Affordable! | F49: Verified Purchase | G49: 10 | H49: 5 | I49: Iâ€™ve been steadily growing my collection of Apple products, and always had the Apple Watch on my list. The SE is the perfect buy for anyone looking for a sleek, stylish, and functional smartwatch at a fair price. It is compatible with the latest iOS and has all of the application features I was looking for (and then some)! Plus it has loads of cute watch faces to choose from - you can even easily switch between faces by adding them to your â€œFavorites.â€ All-in-all Iâ€™m very happy with my purchase! | J49: Electronics
A50: AFN6DF772KMD3NZ4PTZQ3K4YAVAA | B50: PROD049 | C50: Jessica | D50: 45669.572 | E50: Really good! | F50: Verified Purchase | H50: 5 | I50: The delivery was delayed, but the watch is really good! | J50: Electronics
A51: AHQ3IPOJYC432FQKOQ7H5N3X62TQ | B51: PROD050 | C51: Debo | D51: 45670.051 | E51: Nice | F51: Verified Purchase | H51: 5 | I51: Great watch for the money. Goes with most of wife's outfits and she appreciates the fitness tracker. | J51: Electronics
A52: AHOJVFMWNQWI23DEWGYIJY5NUNVA | B52: PROD051 | C52: Tom Venuto, Author of Burn the Fat, Feed The MuscleTom Venuto, Author of Burn the Fat, Feed The Muscle | D52: 45670.2 | E52: Huge toolkit of actionable, practical, organized strategies to build positive habits | F52: Verified Purchase | G52: 2260 | H52: 5 | I52: I've read a lot of books on changing behavior and building habits and James Clear's Atomic Habits is my new favorite. This book is different from others in the way it covers an enormous amount of ground in the larger area of self-improvement while seamlessly tying all these ideas back into the central theme of habits.One of the core concepts in Atomic Habits is to focus on the small improvement. The impact a 1% improvement per day can make may appear negligible at first, but Clear makes a compelling argument that in the case of habits, thinking small produces the biggest results over time. "Habits are the compound interest of self-improvement," explains Clear.Over the months and years, the accumulated effect of small habitual daily behaviors is staggering. Early in the book we are also warned that this compounding works both ways, so we'd better make sure we're making it work in the positive direction, not for the negative.This is a concept I was introduced to years ago under a different name - Kaizen - the Japanese term for continuous incremental improvement. What's different and new in this book is how the concept is applied specifically to building habits.I found the information introduced in chapter two about behavior change at the identity level to be spot-on. You're also given a simple two-step process for changing your identity and this one idea alone is incredibly powerful.In chapter three, we are introduced to the habit loop - cue, craving, response, reward - and we learn how to build good habits in 4 simple steps and break bad habits in 4 simple steps.One of those steps to habit formation, which goes hand in hand with the 1% concept, is how to make it not only small, but easy. In the chapters that follow, this is exactly what you find out.Other ideas of great value that stood out included, habit stacking (the best way to form a new habit), habit tracking, habit shaping and how to design your environment - physical and social - for habit building success. You learn the truth about self-control, how to stop procrastinating and how to use implementation intentions, temptation bundling and motivational rituals. The book is simply packed with actionable ideas, tactics and strategies.Virtually every idea in the book is useful and resonated with me. While I may not agree that we should "forget about goals," I agree with one of Clear's core principles in the book - that we must develop systems for change. If we only focus on goals and don't develop systems and a focus on the process, we risk falling into a number of goal-related traps which ultimately lead to stagnation. With the right systems, we're rewarded with continuous improvement on a lifelong journey of success.Another difference between Atomic Habits and other books in this genre is that while it's based on science it doesn't bog you down with unnecessary details of the research. Clear's book is intensely practical, giving you a huge toolkit of organized and named strategies you can apply immediately to create and strengthen positive habits and stop the negative ones.The book is conversational, and includes many interesting stories, making it easy to read - and hard to put down (I read it cover to cover in one day).It's possible this might become your most highlighted personal improvement book because every page is so chocked full of memorable and quotable gems of advice. | J52: Books and Stationary
A53: AFOO7WNTJ5WCQ6ZWXCSJYSYI5OWQ | B53: PROD052 | C53: Haical Sajovic Haddad | D53: 45670.343 | E53: Updated review after 100 days building small yet lasting habits. | F53: Verified Purchase | G53: 17342 | H53: 5 | I53: I previously wrote this review right after reading the book. Today, February 15th, after applying Jamesâ€™s system for 100 days on a few tiny habits, I feel compelled to share updates with you because they have sincerely worked.I will divide the review into 5 parts. The first part is a summary of the book with short excerpts highlighted while taking notes. Next, I hope to share pieces of advice that have motivated me while building new habits. Following that, I will share how I implemented the first 3 habits throughout these months. Then, some thoughts to whom I would recommend reading the book. Last, there are 4 complementary readings.SUMMARY[Introduction] James starts by sharing personal strategies he implemented to recover from a serious accident in high school. That event forced him to improve the quality of his routine to get his life in order, coming to the conclusion that â€œwe all deal with setbacks, but in the long run, the quality of our lives often depends on the quality of our habits. With the same habits, you will end up with the same results. But with better habits, anything is possible.â€[Section I : The Fundamentals][Chapter 1] Here we learn the power of compounding effect: changes that seem small and unimportant at any given day will compound into remarkable results if we are willing to stick with them for months and years. James explains that â€œbreakthrough moments are often the result of many previous actions, which build up the potential required to unleash a major change.â€ Comparing to habits, he shows that bamboo can barely be seen during the first couple of years while the roots grow underground before exploding for almost 100 feet into the air in a few weeks. From that perspective, we come to understand the best outcomes are generally delayed.[Chapter 2] Based on a 3-layer concentric circle behavior change modelâ€”divided into outcome change, process change, and identity changeâ€”James explains that we should pay attention to our inner identity by focusing on beliefs, assumptions, and values. â€œMany people begin the process of changing their habits by focusing on what they want to achieve. This leads us to outcome-based habits. The alternative is to build identity-based habits. With this approach, we start by focusing on who we wish to become.â€ The strongest changes, then, happen from inside out, starting from our identity, passing through the process, and ultimately changing the outcome.[Chapter 3] In this chapter we are introduced to a 4-step framework, which is composed of cue, craving, response, and reward. James calls it 'The 4 Laws of Behavior Change'. He then explains that we can think of each law as a lever that influences our behaviorâ€”when the levers are in the right positions, they create good habits effortless whereas when they are in the wrong position, it is nearly impossible. Through examples, he explains that â€œthe cue triggers a craving, which motivates a response, which provides a reward, which satisfies the craving and, ultimately, becomes associated with the cue.â€ Together they create a habit loop that, when repeated many times, habits become automatic.[Section II : Make It Obvious][Chapter 4] A primer on how cues play a crucial role in predicting habit formation without consciously thinking about the outcomes. Once our habits become so common, the cues associated with them become essentially invisible because they are deeply encoded. If we want to create better habits, a good idea is to be aware of the cues. James finishes up by sharing a strategy called 'Habits Scorecard'â€”a simple exercise to become more aware of our behavior on a daily basis. We first write down a chronological list of our daily habits and, once we have a full list, we score each habit as an effective, ineffective, or neutral habit. Besides noticing what is actually going on, we can notice if certain behaviors help us become the type of person we wish to be.[Chapter 5] The cues that can trigger a habit come in a wide range of forms, and the 2 most common cues are time and location. When we make a specific plan for when and where we will perform a new habit, we are more likely to follow through. Stacking our habits by pairing a new habit with a current habit is a form to connect our behavior to our own advantage. An example when building a daily journaling habit would be: â€œafter I pour my cup of coffee each morning, I will journal for 5 minutes.â€[Chapter 6] This chapter shows how our environment plays a crucial role in defining habit behaviors. â€œGiven that we are more dependent on vision than any other sense, it should come as no surprise that visual cues are the greatest catalyst of our behavior.â€ To build good habits, then, we should either make desirable cues obvious in our environment or build new habits in a new environment to avoid fighting against old ones.[Chapter 7] One of the most practical ways to break a bad habit is to reduce exposure to the cue that causes it. As James points out, â€œit is easier to avoid temptation than resist it.â€[Section III : Make It Attractive][Chapter 8] James explains how the modern food industry has created products that are more attractive and addictive to consumers, and by doing so he shows that the more attractive an opportunity is, the more likely it is to become habit-forming. Every behavior that is highly habit-forming tends to be associated with higher levels of dopamine. It is the anticipation of a reward that motivates us to take action. â€œTemptation bundling is one way to make your habits more attractive. The strategy is to pair an action you want to do with an action you need to do.â€[Chapter 9] â€œWe tend to adopt habits that are praised and approved of by our culture because we have a strong desire to fit in and belong to the tribe.â€ That said, it is common to pick up habits and behaviors from our parents, peers, and colleagues. There is also a tremendous internal pressure to comply with the norms of the tribe. And, finally, we try to copy the behavior of successful people because we desire success ourselves. One of the best strategies to build better habits is to join a culture where the desired behavior is the normal behavior.[Chapter 10] To avoid unnecessary and detrimental cravings, we should highlight the benefits of avoiding a bad habit by making it seem unattractive. â€œHabits are unattractive when we associate them with negative feelings.â€[Section IV : Make It Easy][Chapter 11] â€œAll habits follow a similar trajectory from effortful practice to automatic behavior, a process known as automaticity. Automaticity is the ability to perform a behavior without thinking about each step, which occurs when the nonconscious mind takes over.â€ The key component is to pay close attention to the frequency we perform a habit, not much for how long we have been practicing it.[Chapter 12] Since every action requires a certain amount of energy, we are motivated to do what is easy. By contrast, the more energy required, the less likely it is to occur. â€œYou don't actually want the habit itself. What you really want is the outcome the habit delivers. The greater the obstacle, the more friction there is between you and your desired end state.â€ That is why we should reduce the friction associated with our habits by creating a prosperous environment to make future actions easier.[Chapter 13] There are decisive moments that deliver an outsized impact every single day. As James puts, these decisive moments are a fork in the road, sending us in the direction of a productive path or an unproductive one. To avoid procrastination, the skill of 'Showing Up' says that we should start a new habit by taking baby steps, making it as easy as possible to take action. â€œA new habit should not feel like a challenge. The actions that follow can be challenging, but the first 2 minutes should be easy. What you want is a gateway habit that naturally leads you down a more productive path.â€ He calls it the 'Two-Minute Rule', meaning that new habits should take less than 2 minutes to do in the beginning. Once the habit is established we can improve and master the finer details.[Chapter 14] In order to keep bad habits away is to make them difficult in the first place. There are 2 interesting strategies to improve our future behavior. [1] Make good choices in advance before we can fall victim to temptation in the future. James gives a personal example by sharing that whenever he is looking to cut calories he will ask the waiter to split his meal and box half of it to go before the meal is served. If, however, he waits for the meal to be served and tries to eat just half, that would never happen. [2] Make onetime actions that can automate our future habits and deliver increasing returns over time such as buying a good water filter, unsubscribing from unwanted emails, moving to a friendlier neighborhood, buying a standing desk, or setting up automatic bill pay.[Section V : Make It Satisfying][Chapter 15] We should make sure to feel immediately satisfied after performing a new habit to increase the odds that the behavior will be repeated next time. â€œThe human brain has evolved to prioritize immediate rewards over delayed rewards.â€ For that, we can add a little bit of immediate pleasure to the habits that pay off in the long-run.[Chapter 16] Here we learn how to measure our progress by tracking our habits. The immediate satisfaction it deliversâ€”as mentioned earlier in Chapter 15â€”is one of the many benefits that standout. Besides that, James says, â€œwhen we get a signal that we are moving forward, we become more motivated to continue down that path.â€ The most basic format to track our habits is to get a calendar and mark an X each time we stick with our routine. One of the most important passages of the entire book is as follows: â€œIf you miss one day, try to get back into it as quickly as possible. The first mistake is never the one that ruins you. It is the spiral of repeated mistakes that follows. Missing once is an accident. Missing twice is the start of a new habit. This is a distinguishing feature between winners and losers. Anyone can have a bad performance, a bad workout, or a bad day at work. But when successful people fail, they rebound quickly.â€[Chapter 17] In order to prevent bad habits and/or eliminate unhealthy behaviors, James says that we could either add an instant cost to the action or make it painful. A habit contract is also another strategy to hold our accountability: â€œIt is a verbal or written agreement in which you state your commitment to a particular habit and the punishment that will occur if you don't follow through. Then you find one to two people to act as your accountability partners and sign off on the contract with you.â€[Section VI : Advanced Techniques][Chapter 18] We learn how to distinguish habits when genes may or may not influence our performance especially for competitive activities. â€œOne of the best ways to ensure your habits remain satisfying over the long-run is to pick behaviors that align with your personality and skills.â€ James proposes us to set some time apart to explore new activities in the beginning, before shifting our focus to exploit them thoroughly.[Chapter 19] When we find the sweet spot of our ability we tend to learn best and fastest. The â€˜Goldilocks Ruleâ€™ states that "humans experience peak motivation when working on tasks that are right on the edge of their current abilities. Not too hard. Not too easy. Just right.â€[Chapter 20] One downside of certain habits, James explains, is that we may stop paying attention to the little details and errors. To counterbalance that we should review and reflect on the process over time to remain conscious of our own performance. Using a simple chart to convey his message, we learn that â€œthe process of mastery requires that you progressively layer improvements on top of one another, each habit building upon the last until a new level of performance has been reached and a higher range of skills has been internalized.â€PERSONAL THOUGHTSReading the book twice helped me take better notes and capture details. In the meantime, I thought about 3 simple strategies that could improve our adherence to new habits. Let me share these strategies here with you, and in the following section, I will describe how I managed to cultivate the first 3 new habits upon reading the bookâ€”following the system proposed by James together with these 3 strategies.[1] The first strategy is about determining a 'commitment time frame' to avoid excuses during this initial trial period. A 1-month time frame is a fair commitment, choosing to start on the first day of the month to practice it every single day for a full month. Just at the end of the period, I will take the time to reflect and evaluate the pros and cons.[2] The next one is to choose only 1 new habit each month. In doing so we become familiar with the practice intentionally while we develop a sense of purpose.[3] Last, during the first month of any new habit, I noticed that if I spend time exploring the details and the benefits, my motivation stays high. It doesn't only help us create better practices, but it is also inspiring to learn from others who have succeeded previously by adding the same habit into their lives. Podcasts, articles, videos, books, online courses, tutorials, and blog posts are all good sources.IMPLEMENTATION OF NEW HABITS[Nov 1, 2018] I had been wanting to journal on a daily basis for many years but that had never happened. Although I have carried a notebook with me for quite a while, it has never worked as a real journalâ€”a daily routine, when we sit down and write personal thoughts, intentions, and reflections at around the same time. Instead, it has been mostly used to take notes during meetings, to write down ideas and thoughts, to express travel memories, and to doodle. Today, after 3+ months, I haven't looked back once, and still can't believe it took me that long to start this daily habit. During the first month, I read blog posts, watched videos, and even read a short and inexpensive book to foster my creativity.[Dec 1, 2018] I have been impressed by the physical capabilities we can develop through body movement. Although yoga has been a special part of my life since I was 18, I hadn't given proper attention to handstands. But now, after 2+ months practicing it every day, it is rewarding to see improvements on a weekly basis. Again, I definitely recommend watching videos and reading tutorials to find your favorite method. This is the perfect habit to stack at the end or in the middle of any physical movement practice you may enjoy.[Jan 1, 2019] By now we know the benefits of cold showersâ€”ranging from healthier skin appearance all the way to a more resilient perspective of the world. I had previously taken cold showers for 3 months in 2017, but it was a â€œgoalâ€ mindset instead of a â€œhabitâ€ mindset. After that trial I set aside and, although I have kept taking cold showers once or twice a week since then, I wished cold showers was the default mode. Now, after 1+ month, I can't see myself taking warm showers. After all, it is about intention. Again, we can learn uncountable benefits of cold showers by reading success stories. One of my inspirations was Wim Hof. It isn't comfortable in the beginning of any chosen day, but after 3-4 minutes, both my breath and thoughts calm down.Putting them together, these 3 habits don't take more than 30 minutes of my day. While I spend about 10 minutes journaling and 10 more minutes practicing handstands, I save 5 minutes taking cold showers because I won't stay any longer than necessary.RECOMMENDATION[1] First, if you have watched videos, listened to podcasts, read articles and books on habit formation and, after all that, you feel satisfied, then, please, save your money and time.[2] However, if you are like me, that even after reading a few books on building habits and having successfully added good habits to your life, feel that there is still room for improvement, this book can be a terrific addition.[3] Last, if you haven't spent much time and energy discovering a good system to build lasting habits while breaking bad ones, please, read this book.COMPLEMENTARY READINGS[1] Game Changers, by Dave Asprey, exposed me to a wealth array of ideas/habits/tools that have helped me decide which new habit to build next. The book is divided into 46 laws.[2] Essentialism, by Greg McKeown, helped me focus on less but more important tasks, giving clarity to what matters most. This is especially interesting to break bad habits.[3] The Talent Code, by Daniel Coyle, brought more motivation when learning new skills based on the assumptions that we develop new talents through deep practices, finding our ignition identity, and having the right coach to guide us genuinely. I read it many years ago, then, a few years back, I read his following book called The Little Book of Talentâ€”which is perhaps even more to the point.[4] The Systems View of Life, by Fritjof Capra, enlightened my perspectives on how nature and living beings are systematically integrated. It is a profound and slightly academic book that can complement Atomic Habits especially to tie together the 4-step framework into the feedback loop system.I sincerely hope you, too, have fun while building new habits.Take care,Haical | J53: Books and Stationary
A54: AFIYLH7AIYLQEKPDV7EIYPMIJJEA | B54: PROD053 | C54: Mike PritchardMike Pritchard | D54: 45670.466 | E54: Atomic Habits will change your life! 9 takeaways: | F54: Verified Purchase | G54: 587 | H54: 5 | I54: Atomic Habits by James Clear is one of those rare books that I immediately read twice in a row. It is filled with dozens of science-backed and actionable nuggets of wisdom. Do you want to improve any habits in your life? I heartily recommend Atomic Habits to you! We are all driven by our habits - many of which are unconscious. Below are 9 quotes and takeaways from this life-changing book:1. "Getting 1 percent better every day counts for a lot in the long-run." Atomic Habits explains why the little things you do every day matters. Your little habits matter. It may not seem like a big deal to skip a workout or to be kind, but it is a big deal. Imagine if you improved your habits by only 1% every day. You'd be dramatically a different person in a year. Then imagine if you let your habits decline by 1% every day. You'd be in a much worse spot in life overall a year from now. Your little habits - atomic habits - count for a lot in the long run. What little habits are you improving upon (or neglecting...) today?2. "You do not rise to the level of your goals. You fall to the level of your systems." This is such an important point in the book. Oftentimes we focus on goals in our life, while neglecting to focus on the systems that help us achieve goals. As an example, I had a friend who had the goal to complete a triathlon. He achieved this goal! And then he quit working out for the next year and got out of shape... He was so focused on achieving a goal that he neglected his underlying systems of being healthy. Goal achievement can actually set us back if we don't get set up sustainable systems. Get the systems right and then we'll indeed also achieve our goals. Systems > Goals.3. "Every action you take is a vote for the type of person you wish to become. No single instance will transform your beliefs, but as the votes build up, so does the evidence of your new identity." I love this quote from the book. Every action - every habit - you take casts a vote for the type of person you want to become. Do you want to be a more organized person? When you develop habits and systems that organize your life, you are casting votes for thinking of yourself as an organized person. You think to yourself, "hey, I'm an organized person." And then you reinforce that belief with your habits and actions - a virtuous cycle! The flip side of this can be true too. What if you often show up late to meetings? You're casting votes that may make you think "well, I'm just a person that is always late." An un-virtuous cycle. Be careful to make sure that your habits and ultimately your beliefs cast votes for the type of person you want to become and, indeed, who you truly are.4. "How long does it actually take to form a new habit? You just need to get your reps in." Atomic Habits answers the question of "how much time does it take to form a new habit" with a better answer of : X number of actions. Meaning, you may need to simply complete a new habit 100 times for it to stick, which could be done in 3 days or 3 weeks or 3 months, depending on the new habit. It is better to think of forming new habits in terms of consistently taking action, versus trying to stick to a habit for just X number of days. Get your reps in.5. "Reduce friction. Decrease the number of steps between you and your good habits." The inverse of this is also true - increase friction between you and your bad habits! I think about this a lot when it comes to eating healthy. I need to reduce friction by having healthy food in the house and healthy snacks at work. And I need to increase friction by not having candy in the house or in my office! Out of sight, out of mind. In sight, and I eat it. :) (which of course reminds me of the Dad joke I often tell my girls: "I'm on a seafood diet. I see food and I eat it...)6. "Use temptation bundling. Pair an action you want to do with an action you need to do." This is a powerful concept. I put this in practice by only "watching TV" when I'm on the treadmill. I am able to run at a 6 MPH pace and watch TV or videos on the iPad when I'm on a treadmill. So, I generally only watch sporting events or movies or 80s music videos on YouTube when I'm running on the treadmill. This approach actually allows me to run longer if I want to watch a full half of a game, for example. And 80s music videos will often give me the energy to run that extra mile. :) Think about a new habit you want to start and how you can bundle it with an action you're already taking. Stack them together - i.e. habit stacking.7. "Use a habit tracker. Keep track of your habit streak and 'don't break the chain.'" Atomic Habits does a nice job of explaining the importance of tracking your habits for success. What gets measured gets managed. One of my favorite habit trackers is a FitBit/Apple Watch, which tracks steps, heart rate, sleep, weight and can even track food intake/calories, if you input this data. My behavior definitely changes thanks to these habit trackers. Atomic Habits gives you additional habit tracker resources.8. "Never miss twice. When you forget to do a habit, make sure you get back on track immediately." We all will have days where we fall off the bandwagon and our habits go in reverse. Well, that's okay for one day. Don't let it happen twice. Get back on track as soon as possible. (And, yes, sometimes we miss a habit two days in row. Just don't let it become three days...)9. Author James Clear gets to the point quickly in Atomic Habits and with actionable advice. James has been blogging about habits, health, happiness, creativity and productivity since 2012. Check out a sampling of his writing at his website. James is also fun to follow on Twitter. Atomic Habits has 20 relatively short chapters that open with compelling stories and end with helpful chapter summaries. If you listen to books on Audible, I highly recommend the audio book as James reads this book very passionately. | J54: Books and Stationary
A55: AF3BU2FPKRUWQSRPTJLJVBPRDCDQ | B55: PROD054 | C55: Amazon Customer | D55: 45670.676 | E55: Tiny Baby Steps | F55: Verified Purchase | G55: 7 | H55: 4 | I55: This book is an excellent example of how small infinitesimal changes add up over time. You don't have to bite off more than you can chew. Rather, start small, and build upwards in order to improve your overall life. Plenty of real life examples as well as charts and illustrations that keep the reader engaged throughout. A must read for anyone needing a life boost. | J55: Books and Stationary
A56: AG62UD7Q67DBARLYYTGSWHASW33Q | B56: PROD055 | C56: Amazonlover | D56: 45670.957 | E56: Transforming Through Tiny Changes: A Deep Dive into 'Atomic Habits | F56: Verified Purchase | G56: 119 | H56: 5 | I56: My journey with "Atomic Habits: An Easy & Proven Way to Build Good Habits & Break Bad Ones" has not just been enlightening, but it has been an absolute game-changer for my personal development. I began this exploration with a hint of skepticism and concluded with an undeniable realization of its potential. "Atomic Habits" is not just another self-help book; it's a guide, a mentor, and a blueprint that ignited my drive for growth in ways I never foresaw.While it's nearly impeccable in its approach, there are a few nuances that could resonate differently with readers. Eager to provide an objective viewpoint, I'll dive into my thorough experience with this book, offering an insider's perspective on its profound layers. This review is packed with my praises, yet it also touches on areas where the content could be slightly refined for broader appeal.ðŸ–¥ï¸ðŸ“š **Detailed Strategy Over Mere Concepts**: A refreshing twist in self-help literature: At first read, it's evident that "Atomic Habits" isnâ€™t just about abstract concepts. Instead, it offers actionable strategies, a pivot from the norm that significantly influenced my approach to habit formation. Its emphasis on the power of compound growth resonates deeply, bridging the gap between mere knowledge and its practical application.ðŸ’¡ðŸŒ™ **Micro Changes, Macro Impacts**: Illuminating the potential of the minuscule: One of the standout features of the book is its emphasis on small changes leading to profound impacts over time. This concept is relatable, especially for those who've faced the daunting task of overhauling their lifestyles overnight. Itâ€™s these minor tweaks, consistently applied, that can shape destiny, a theme consistently echoed throughout the book.ðŸ“šðŸŽ’ **Science Meets Anecdote**: A Blend of Research and Real-Life Stories: James Clear masterfully intertwines scientific research with personal anecdotes, painting a comprehensive picture of habit formation. This duality provides both a theoretical foundation and relatable stories, enhancing the book's credibility and readability.ðŸ•¶ï¸ðŸ–ï¸ **Crisp Presentation Coupled with Engaging Narration**: A Treat for Avid Readers: The coherent structure and lucid style of "Atomic Habits" are commendable. But the true gem is its captivating narrative, which ensures readers are glued from start to finish. It feels less like a study of habits and more like an enlightening conversation with a trusted friend.ðŸ”‹â±ï¸ **Sustained Motivation as the Central Theme**: The Powerhouse of Habitual Evolution: The recurring theme of maintaining motivation is a testament to the book's holistic approach. By focusing on systems over goals, it provides readers with a blueprint for long-term success, making transient motivation bursts a thing of the past.However, in the spirit of a well-rounded review, I'd like to touch upon a minor observation:âš–ï¸ðŸ¤” **Overemphasis on Certain Concepts**: Repetition for Reinforcement, or Redundancy?: While the recurring themes reinforce the book's core concepts, there are instances where certain ideas felt slightly overemphasized. While some readers might find this repetition helpful, others might see it as a tad redundant.Considering everything, "Atomic Habits" overwhelmingly earns its 5-star rating ðŸŒŸðŸŒŸðŸŒŸðŸŒŸðŸŒŸ. Any minor repetitiveness pales in comparison to the goldmine of insights this book offers. The meticulous research, relatable anecdotes, and actionable strategies make it a must-read.To all individuals eager for personal growth and those on the fence about diving into the realm of habits, I wholeheartedly endorse "Atomic Habits". It promises transformative insights and practical tools to craft a better version of oneself. After all, don't we all seek a life of improvement, one habit at a time?I extend my deepest thanks to you for investing your time in this comprehensive review. I trust it aids in your decision-making journey, drawing you a step closer to finding your perfect self-improvement guide. To a future enriched with continuous growth, one habit at a time. Dive in, evolve, and thrive! ðŸ“šðŸ’«ðŸŒ | J56: Books and Stationary
A57: AFJWILVUKZTXLMXJCBMMTQMVZAVA | B57: PROD056 | C57: Scott Romney | D57: 45671.942 | E57: Focusing on habits has changed my life | F57: Verified Purchase | G57: 4 | H57: 5 | I57: This book was a game-changer for me. I have taught my children, my employees, my friends, the folks I go to church with, etc. about the main points from this book. I no longer focus on goals, I focus on building better habits and using habit stacking. I have habits that I'd tried to develop for decades to no avail that I now have been doing daily for 2-3 years using the psychology from this book. My all-or-nothing personality benefited greatly from implementing the idea of showing up for 2 minutes, making it so easy that it didn't make sense not to do it, and then the habit grows from there. I think James Clear does an amazing job explaining these concepts. I am a huge fan of this book, and I've gotten several other people to incorporate these concepts so they can change their lives for the better as well. I feel better about myself and no longer beat myself up come New Year's, because it's not about reevaluating myself at the start of each new year. Now it's a daily process to focus on habits and get a little better as I go. I use a habit tracker every single day without fail, and there are some habits that are non-negotiable that I complete no matter what is going on in my life. These concepts truly work! | J57: Books and Stationary
A58: AH3CO6FCIGKQ3Y6RLQKN7AJRA5RA | B58: PROD057 | C58: Kurt Witowski | D58: 45671.992 | E58: A â€œMust Haveâ€ For Young Adults | F58: Verified Purchase | G58: One | H58: 5 | I58: â€œAtomic Habitsâ€ pinpoints effective choices that catapult remarkable results. A friendly and down-to-earth vibe makes it a joy to read. Donâ€™t let that fool you though â€” significant thought and effort went into this book, making it a wealth of excellent suggestions. Lifeâ€™s too short to make all the mistakes yourself. Thatâ€™s why itâ€™s good to learn from books and other people.As if the book wasnâ€™t already an outstanding value, James will support you with links and even bonus material (email proof of purchase) if you like. The man has done his homework and then some. Not hard to see why itâ€™s sold over 15 million copies. If you want to achieve maximal effectiveness while still enjoying the process then â€œAtomic Habitsâ€ is for you. | J58: Books and Stationary
A59: AFJJBXPYP5ANFCWQJ2KEEMYBL4MA | B59: PROD058 | C59: Ines | D59: 45672.252 | E59: A Game-Changer for Building Lasting Habits | F59: Verified Purchase | G59: 16 | H59: 5 | I59: I canâ€™t recommend Atomic Habits enough! This book is a complete game-changer when it comes to understanding how habits work and how to create positive, lasting change in your life. James Clear breaks down the science of habit formation into simple, actionable steps that anyone can apply.What I love most about this book is how practical it is. Clear doesnâ€™t just talk about the importance of habits or motivational theories; he gives you a clear, step-by-step approach to making real change. His "1% improvement" philosophy is so refreshingâ€”itâ€™s all about making small, incremental changes that, over time, lead to huge results. This approach feels more achievable and sustainable than the typical â€œall-or-nothingâ€ advice we often hear.The book is packed with insightful strategies for building good habits (like habit stacking and the 2-minute rule) and breaking bad ones. Clear also dives into the psychology behind habits, showing how environment, identity, and consistency play crucial roles. I found the examples and case studies particularly helpful for understanding how to apply these ideas to different areas of life, whether itâ€™s fitness, productivity, or personal growth.Since reading the book, Iâ€™ve implemented several of his strategies, and Iâ€™ve already noticed positive changes. Iâ€™ve been able to stick with new habits in a way I never could before.If youâ€™re looking to make lasting changes in your life and break free from old, unproductive habits, this book is a must-read. Itâ€™s one of the best personal development books Iâ€™ve read in a long time and is now a go-to recommendation for anyone trying to improve their habits.Let me know if you find this helpful, I hope it is! I put a lot of effort and time writing these reviews so it would be greatly appreciated! | J59: Books and Stationary
A60: AH3COXJMS7ZLFUJS4FV2X2K3EL3A | B60: PROD059 | C60: Zbunny | D60: 45672.377 | E60: Small changes make a big difference | F60: Verified Purchase | H60: 5 | I60: This book really helped me reshape my habits over time. By "showing up" every day, even if I just do a 2 minute version or 5 minute version, I have now formed habits that have lasted 2 years so far, and I think they are deeply embedded enough that they will last a lifetime.Some of my habits include morning bible study (habit stacked) but also taking a 15 minute walk during my mid-morning break (and if it's stormy outside I switch to squats, planks, lunges, etc.).I also habit stacked my whole morning: wake up>deep breathing>brushing teeth>grounding for 3 minutes>drinking 12 oz water>showering>skin care>bible study and prayer>dress and out the door by 6:00 am). I've never felt healthier or more at peace with myself and the world. I've also shared these ideas with my students to get them to make small changes for a big impact in their life trajectory. Some run with it, some ignore it, but at least the idea is planted in their brain. | J60: Books and Stationary
A61: AEPO2M5PT34MN74SUW2CGNUZWESQ | B61: PROD060 | C61: S. H. Nager | D61: 45672.858 | E61: Good | F61: Verified Purchase | H61: 4 | I61: This is, again, my opinion:It started off well. It is somewhat simplistic, but it hits enough key points. I understood he overcame his setback with what he wanted with sports. It was a good grounding of what he achieved.We got ideas on how to work on habits, ideas on daily/life practices, touched on many aspects of everyday lives, and how we look at things. It was interesting.Then, the end, again for me, nose-dived heavily into sports analogies, and he lost me. It became too focused on this aspect.I will be using this book for freshmen in college, as a peer highly recommended it. We'll see how they analyze it and report on the book.Before I read the book, my only qualm was the word "Law" for the sections. It still bothers me.I did enjoy the first 2/3's. I know many feel this is an excellent book. My four stars are for what I wrote above. Again, my opinion. | J61: Books and Stationary
A62: AE63ONDBAUZOOQRORRRL3XI4UPVQ | B62: PROD061 | C62: Jonathan Massey | D62: 45673.039 | E62: This Book Was So Good, I Bought It Twice! | F62: Verified Purchase | H62: 5 | I62: I rarely write reviews, but Iâ€™m making an exception because James Clearâ€™s work has genuinely impacted my life. I first listened to Atomic Habits on Spotify and loved it so much that when James offered a bonus chapter for purchasing the book, I didnâ€™t hesitate to spend my hard-earned money on a physical copyâ€”despite already having access to it. Thatâ€™s how much value I found in this book.This review probably isnâ€™t necessary given the bookâ€™s massive success, but I felt compelled to write it because of how much James Clearâ€™s content continues to benefit me. His 3-2-1 newsletter is the only one I consistently read every week, and I even make a point to revisit it if I donâ€™t have time initially.Atomic Habits isnâ€™t just a bookâ€”itâ€™s a guide that inspires action, and I highly recommend it to anyone looking to make meaningful changes in their life. | J62: Books and Stationary
A63: AGZWQJBHTLOR3LQTBDVMSZSQEYWA | B63: PROD062 | C63: P. Carn | D63: 45673.31 | E63: FILLED WITH NUGGETS | F63: Verified Purchase | H63: 5 | I63: I read a library copy of this book, cover to cover, about three years ago. I am not, I repeat NOT, a self-help book type. I found this book so helpful, however, I proceeded to purchase my own copy so I could highlight passages, make notes in the margins and turn it into a life reference book. And then I purchased an audio version... Unlike the sappy pabulum found in many other self-helps, this book gave me solid NUGGETS that provoked deep reflection into areas that prompted true personal growth. PLUS, it helped me create one-sentence prompts that I could burn into mind and pull up when immediate motivation was needed. For instance when I feel lazy, I ask myself, "What would a healthy person do?" I lean into his concept of identity-based habits rather than outcome based habits. I routinely revisit Atomic Habits. More than any program, or personality, this way of embracing change has impacted numerous areas of my life. Thank you! | J63: Books and Stationary
A64: AFYQP34WCN2L7ZPODP4J4LAOV4ZQ | B64: PROD063 | C64: Kathleen Shannon | D64: 45673.434 | E64: Mary Poppins for adults | F64: Verified Purchase | G64: 3 | H64: 5 | I64: James Clear might not like this comparison but his book reminded me of certain lines in Mary Poppins. â€œFor every job that must be done there is an element of fun. You find the fun and snap the jobâ€™s a gameâ€. Establishing new habits or desperately trying to rid myself of bad ones made me feel like I was checking off a list of chores. Mr. Clear brings joy and satisfaction to habit making and breaking with his innovative and unique ideas. He actually makes the whole process exciting. Yes, as he says life is short. Before you know it youâ€™re 60. However, with this easy and inspirational book Iâ€™m ready to take on new habits and ditch the bad ones. Mr. Clear proves that you can teach an old dog new tricks. | J64: Books and Stationary
A65: AGG5ADSURYJDEQDWHIND5NBLWWFQ | B65: PROD064 | C65: ARHuelsenbeck | D65: 45673.48 | E65: You will be familiar with much of the material in this book. You've heard it before. | F65: Verified Purchase | G65: 15 | H65: 4 | I65: I bought Atomic Habits: An Easy & Proven Way to Build Good Habits & Break Bad Ones by James Clear because it had been recommended to me so very many times. I was already familiar with Clear because Iâ€™ve read many of his articles and I subscribe to his newsletter.You will be familiar with much of the material in this book, because there are so many self-help resources out there and on the internet, but itâ€™s nice to have it all collected in one place. Also, Clear helps you analyze what you want to improve in your own life and gives you helpful strategies to do that. He identifies four laws to help you form good habits, and points out that to break bad habits you need to invert the four laws.Here are some sentences from the book that I underlined:Be far more concerned with your current trajectory than with your current results.You get what you repeat.In order to make a meaningful difference, habits need to persist long enough to break through the plateau of latent potential.Becoming the best version of yourself requires you to continually edit your beliefs, and to upgrade and expand your identity.Desire is the engine that drives behavior. Every action is taken because of the anticipation that precedes it.When changing your habits means challenging the tribe, change is unattractive. When changing your habits means fitting in with the tribe, change is very attractive.The most effective form of learning is practice, not planning.The amount of time you have been performing a habit is not as important as the number of times you have performed it.Direct your effort toward areas that both excite you and match your natural skills, to align your ambition with your ability.When you canâ€™t win by being better, you can win by being different. By combining your skills, you reduce the level of competition, which makes it easier to stand out.Reflection and review enables the long-term improvement of all habits because it makes you aware of your mistakes and helps you consider possible paths for improvement.Each of the 20 chapters includes anecdotal illustrations and a summary at the end.Atomic Habits is a book that I will be rereading regularly. | J65: Books and Stationary
A66: AEAKEDWXDU7I5WTIAF2VNNYGRJLQ | B66: PROD065 | C66: Natalia Castano | D66: 45673.494 | E66: Great gift with practical insights | F66: Verified Purchase | H66: 5 | I66: I bought this book as a gift, and my friend absolutely loved it. The hardcover format adds a nice touch, making it feel even more special.She mentioned that the book has been incredibly helpful in creating new habits and breaking bad ones. Itâ€™s practical, well-written, and full of actionable advice. Highly recommend it as a thoughtful gift or for anyone looking to improve their daily routines! | J66: Books and Stationary
A67: AEDPRDHBU3YLOCQUKNDUZNMTU3BQ | B67: PROD066 | C67: tyester | D67: 45673.624 | E67: This book has already become ingrained in our culture | F67: Verified Purchase | H67: 5 | I67: If you haven't read this yet, you'll be surprised at how much of it sounds familiar when you DO read it. I just finished reading the paper copy (listened to Audible first time around) and I was thinking to myself that I will miss reading this book. I'm maybe starting to understand why people read this more than once. It inspires habit change in ways that are completely attainable and the various methods described allow each reader to come at habit change in whatever way suits them best. Each topic is treated in depth, so I imagine that's the allure of the re-readsâ€”you'll pick up something from one of the approaches that didn't resonate last time. I'll continue to refer to the contents of this book going forward. | J67: Books and Stationary
A68: AGDOPXBUVJC72XHYDYXNYXDEFRDA | B68: PROD067 | C68: A Colorado bookworm | D68: 45673.635 | E68: A digestible, applicable, memorable self help book | F68: Verified Purchase | H68: 5 | I68: Iâ€™m not usually a big self help reader, or, if I am, itâ€™s usually coming from a different angle. But my book club was reading this, so I went for it. Andâ€¦drum roll, pleaseâ€¦I loved it! It made me aware of my all or nothing, subconscious ways of thinking, which have influenced so much of my life. I intend to make this book a reference manual for being resilient in building habits I wish to grow and maintain and in letting go of behaviors and thought patterns which have held me back or held me hostage. Thanks, James! | J68: Books and Stationary
A69: AFM5UF7HWHO2FMJLASKH6M6Z4ZTA | B69: PROD068 | C69: Lenore Burgi | D69: 45673.95 | E69: Led me to a great app. | F69: Verified Purchase | H69: 5 | I69: This book is helping me achieve my goals. I love that Mr. Clear gives a step by step process; baby steps toward becoming the person you wish to be. I appreciated the free downloads and mostly I love the app for Atomic Habits. It reminds me and tracks my progress. I feel like I am breaking through toward becoming more. | J69: Books and Stationary
A70: AG5FZB3PUDZQ2QANJ3QLI2K774TQ | B70: PROD069 | C70: Shontelle Logan | D70: 45674.245 | E70: A Gentle Reminderâ€¦ | F70: Verified Purchase | G70: One | H70: 4 | I70: I did enjoy this book and I feel like it would be arrogant for me to say I didnâ€™t learn ANYTHINGâ€¦ But for the most part, I feel like this book was a good reminder of things I knew, but forgot about. It did a good job of explaining the concepts and gave good examples of putting the concepts into practice. I also found myself discovering that there are actually names for some of the things I already do. All in all, I felt like this was a great book and a good place to start if you have your mind in the right space to start making some big changes in your life by beginning with some very small habits. *hugs ðŸ™ðŸ¾ðŸ’œðŸ¦‹ | J70: Books and Stationary
A71: AHMIJSZ6Y2XYTDAYRNV327JDW3CA | B71: PROD070 | C71: SC | D71: 45674.874 | E71: Glad this book came to me! | F71: Verified Purchase | H71: 5 | I71: This book was recommended to me by a friend and I have to remember to thank them. Wonderful self help book. I have already started using some of the suggested methods with positive results. Give the book a try, you will be glad you did! | J71: Books and Stationary
A72: AE4AGH5233UP5VQSBHHNRQIHSDGA | B72: PROD071 | C72: Randall SRandall S | D72: 45674.951 | E72: Helpful Info about Habit Breaking and Making | F72: Verified Purchase | H72: 4 | I72: This book breaks down what it takes to build a new habit and get rid of a bad one. Chapters are reasonably short and scientific explanation of habit construction is very readable. There are some personal examples but mainly consists of explanation of how habits are built or broken, specifically "cue, craving, response and reward." There are good examples of what it takes to build a good habit (make it obvious, make it attractive, make it easy, make it satisfying) as well as how to break ourselves from bad habits by distancing us from the cues that spark these habits and building mental and physical barriers that make these habits invisible, unattractive, difficult and unsatisfying. This was a good read, and the concepts explained here will apply to multiple aspects of our lives. | J72: Books and Stationary
A73: AG7DFXXPS5PNARCPXGX5Y6SE5PKA | B73: PROD072 | C73: Virginia Vasquez | D73: 45675.122 | E73: Great book and will make a great gift as well. | F73: Verified Purchase | G73: One | H73: 5 | I73: Excellent book, finally got to read it. A must read transforming book that will help you form good habits. A â€œMust Haveâ€ For Young Adults, I will be gifting this book to my son on his 14th birthday. | J73: Books and Stationary
A74: AHL4PUMBLEFOFIWCJH2ONF2T322A | B74: PROD073 | C74: Andreas Aristidou | D74: 45675.238 | E74: Distilled and clear ideas made into a simple system of behavior change. Top notch! | F74: Verified Purchase | G74: 55 | H74: 5 | I74: I began reading this book with very high expectations and it did not disappoint. I, myself, am a big believer of the power of habits and have done a lot of research on the topic. Yet I learned a lot, especially the clarity with which the author presents his ideas. Big parts of the book were, in some sense, confirmation that I was doing things the right way, since I was oftentimes thinking "oh yeah, that's similar to what I'm doing". Still, parts of the book and strategies proposed were new to me and really helped add habit strategies to my toolbox. As mentioned though, the best thing about this book is the clarity with which the ideas are presented and the way they blend together.This quote from the last chapter summarizes the "Four Laws of Behavior Change" (that the book is about) well: " (1) Sometimes a habit will be hard to remember and you'll need to make it obvious. (2) Other times you won't feel like starting and you'll need to make it attractive. (3) In many cases, you may find that a habit will be too difficult and you'll need to make it easy. (4) And sometimes, you won't feel like sticking with it and you'll need to make it satisfying."Here's some of the notes I made while reading the book:- Habits are like compound interest in self-improvement.- Outcomes are a lagging measure of habits.- The "Valley of Disappointment" is the period where you are putting in the hard work but still seeing no results. --> but remember, your work is not being wasted, it is being stored.- You do not rise to the level of your goals, you fall to the level of your systems.- Your habits shape your identity and your identity shapes your habit. It's a feedback loop. (reverse causation for the nerds here)- Make clear plans - Use the "Implementation Intention": When X happens, then I will do Y OR if Z happens, then I will do W.- Use "Habit Stacking": After behavior X, I will immediately perform behavior Y OR If Z happens, I will immediately perform behavior W. (i.e. As soon as I begin boiling water for tea, I will do 10 burpees). Also, be very clear. (i.e. I will do the burpees next to the fridge in the kitchen, or whatever, you get the idea. As long as it works, it's good!)- People with high self-control are the ones who structure their environments in such a way to minimize exposure to tempting situations.- Use "Temptation Bundling" + "Habit Stacking": After X, i will Y. Right after Y, I will immediately Z,where X - habit I already do, Y - habit I need to do, Z - habit I want to do. (The anticipation of a reward is what gives us the most motivation - and not the reward itself.)- Do something you enjoy before a difficult habit.- Planning can sometimes be a form of procrastination because it can make you feel like you are making progress (while you are not).- Make your habits as easy as possible to start (i.e. do one set of abs, read one page of my book) - This is called a "Gateway Habit". and it helps to reinforce your identity of who you are which will itself help motivate you to keep going.- Prime your environment for future use - "resetting your environment" (i.e. Take out your coffee and mug the night before, make your bed perfectly, to remove the sense of sleep / bedroom if you'll be working from your bedroom)- Use pre-commitment devices to make it harder/ impossible to deviate from good habits.- Even one minute of a bad habit (i.e. checking instagram) can manifest into a lot (i.e. getting lost in time browsing instagram).- Put some immediate reward into good habits / immediate punishment to bad habits.- Create a habit tracker / calendar to provide a sense of accomplishment and motivation.- Rule: Never miss a habit twice! (life gets in the way, but don't let it derail you off your path)- Finding what you are naturally gifted in will make good habits easier. To do that ask the following questions. (1) What feels like fun to me but work to others? (2) What makes me lose track of time? (3) Where do I get greater returns than the average person? (4) What comes naturally to me?- You can also win by being different, by rewriting the rules (i.e. by combining your unique set of skills)- Periodic reflection and review can enable the long-term improvement of all habits - identity building.Finally, some quotes I liked:- "Really successful people feel the same lack of motivation as everyone else. The difference is that they find a way to show up despite the feelings of boredom."- "The greatest threat to success is not failure, but boredom."- "You have to fall in love with boredom."- "Improvement is not just about learning habits, it's also about fine-tuning them."- "Success is not a goal to reach or a finish line to cross. It is a system to improve, an endless process to refine."And my favorite:- "It is remarkable what you can build if you just don't stop." | J74: Books and Stationary
A75: AHJQFJU2YHED6MATIIW37GZE6BUA | B75: PROD074 | C75: DoctorMickey | D75: 45675.677 | E75: I hate giving 5 stars, too much rating inflation, but this one deserves it. | F75: Verified Purchase | H75: 5 | I75: Donâ€™t let the title â€œAtomicâ€ dissuade you. It is how tiny (atomic level) behavior changes can lead to massive (atomic explosion) gradual changes. I was an undergrad. Science major where the majority (66%) were defined as average. Thus 3 star should be the most common rating and not a bad one. I tend to ignore most 5 star ratings, but I do believe this book is 2 standard deviations above the norm. Iâ€™ve listened to this book several times, and have a hard copy to study. A second grade teacher was quoted as saying â€˜if a job/project is too hard, take smaller stepsâ€™ | J75: Books and Stationary
A76: AEG7HBO5ETXGTSGVU5XCUP6MWVZA | B76: PROD075 | C76: Veronica 59 | D76: 45675.796 | E76: Best Book on Habit Formation | F76: Verified Purchase | H76: 5 | I76: I've read a number of books on habit formation. This is not only the best book, but the only one I would recommend. The author covers the nuances of habit formation (or getting rid of a bad habit) from a number of directions and gives you many concrete ideas for solidifying the new habit (or getting rid of the old habit) into your life. | J76: Books and Stationary
A77: AFYQOZJ4IJUMV2QLPXJ7RBWDHM3A | B77: PROD076 | C77: Susan | D77: 45675.861 | E77: Life-changing Book. My favorite book of all time. | F77: Verified Purchase | G77: One | H77: 5 | I77: MY FAVORITE BOOK OF ALL TIME. This book changed my life, especially in regard to helping me get out of a victim mindset where everything was always "happening" to me instead of me taking responsibility to become the person I want and need to be for my family and friends. I hope you choose to read it, it will change your life in practical ways and give you the tools you need to grow. Also, no fluff, every word is meaningful and helpful. JUST BUY IT! If you don't like it, return it. But it's worth it! | J77: Books and Stationary
A78: AHNLNFD2RENWQFBISKE3JO3X7EKQ | B78: PROD077 | C78: James Walker | D78: 45675.948 | E78: Functional, Realistic Strategies for Success in Life | F78: Verified Purchase | H78: 5 | I78: It works. The information is succinct and to the point with just enough explanation to not be overbearing. If you apply it you will quickly find that it works. For any topic of endeavour because human potential is universally based on the basic, fundamental principles exploredDo yourself a favour and read. You will develop and grow from it. Even if you only glean a few nuggets that information will be carried with you for a lifetime as you apply it to your pursuits in life | J78: Books and Stationary
A79: AEPE3NE55F7XWH7IKXR2FS4H7XVQ | B79: PROD078 | C79: Amy Simenson | D79: 45676.298 | E79: The book will change your life! | F79: Verified Purchase | H79: 5 | I79: I've read this book several times. Each time, I get something new out of it. It's an easy read, full of knowledge and skills that you can immediately begin to apply to your own life. James Clear writes in a way that feels like you're having a conversation with a close friend or mentor. So many "aha" moments of realization and practical strategies for improving your life, one small change at a time. If you've been on the fence about reading this one, it's time. It'll easily become one of your favorites! | J79: Books and Stationary
A80: AHP7T6TYPYEITN3VY5EVZQKIVS2A | B80: PROD079 | C80: Maddy | D80: 45677.047 | E80: The book =10/10; The delivery=1/10 | F80: Verified Purchase | H80: 5 | I80: The book is amazing!! the delivery speed was awesome! the issue? the book was delivered in a massive box, with absolutely no filler. the book was thrown around and every corner is now round and messed up instead of good condition. i just donâ€™t think thatâ€™s acceptable ðŸ¤·â€â™€ï¸ | J80: Books and Stationary
A81: AHSI3XBTDDHLR2MVXM3O3XJKRCEQ | B81: PROD080 | C81: Alex CovtunAlex Covtun | D81: 45677.473 | E81: Transformative and Practical â€“ A Game-Changer for Building Habits | F81: Verified Purchase | G81: 3 | H81: 5 | I81: Atomic Habits: An Easy & Proven Way to Build Good Habits & Break Bad Ones by James Clear is a game-changer when it comes to personal growth and habit formation. Clear breaks down the science of habit building in an accessible, practical way, offering a step-by-step guide on how to make small changes that lead to big results over time. His advice on how to focus on systems rather than goals, and how to make habits more manageable and rewarding, has been incredibly helpful in my own life.What I appreciate most is how the book emphasizes the power of incremental improvement, showing that tiny adjustments can compound into major transformation. Clearâ€™s writing is clear, engaging, and filled with actionable insights, making it easy to understand and apply the principles.If youâ€™re looking to improve your habits, whether for personal growth, productivity, or health, Atomic Habits is an essential read. Highly recommended! | J81: Books and Stationary
A82: AGAVKTOX5HJF54F7FJ4SZC3QIXOQ | B82: PROD081 | C82: Soxguy | D82: 45677.503 | E82: Baby steps | F82: Verified Purchase | H82: 5 | I82: I personally love the book and have used it as inspiration to start a morning yoga habit and also to read at least 10 minutes every day. I found it worth the money and time investment. | J82: Books and Stationary
A83: AGAZ34K26PDGIXDAHBN74ZL3B2KQ | B83: PROD082 | C83: kimberly | D83: 45677.529 | E83: Atomic Habit | F83: Verified Purchase | H83: 5 | I83: Learned so much from this book! Great and easy read. This book shows you not only how to establish good habits but ways to break the bad ones. | J83: Books and Stationary
A84: AGWZO32SUGSJDFM6N3OVUCZZBDPQ | B84: PROD083 | C84: Agel | D84: 45677.647 | E84: Easy to Read (Iâ€™m beginning to read books again) | F84: Verified Purchase | H84: 5 | I84: Atomic Habits is easy to read, interesting, and insightful. It breaks down habit formation into simple, practical steps, making self-improvement feel achievable. A must-read for anyone looking to build better habits. | J84: Books and Stationary
A85: AEF4KZXAOMPUFCZK2KBQF7MF7FSQ | B85: PROD084 | C85: Alberta M. | D85: 45677.728 | E85: Why You Need this Book | F85: Verified Purchase | H85: 5 | I85: I've been reading quite a bit lately. This book is definitely one of the most practical reads, one that I will read over and over again. I really love that it comes with a workbook. This really puts things into perspective with real change on the horizon and one that lasts and continues to grow. I highly recommend this book. | J85: Books and Stationary
A86: AEC5HY52RVXC52OAJ5AJQRNGPA3A | B86: PROD085 | C86: Amazon Customer | D86: 45677.953 | E86: A great piece | F86: Verified Purchase | H86: 5 | I86: a wonderful practical book to help everyone understand the changes in life , keep referring to the contents of this masterpiece for your better future | J86: Books and Stationary
A87: AE3TD64LLO4FCUX5BOUERQRPJHRA | B87: PROD086 | C87: J L | D87: 45678.044 | E87: A Comprehensive & Encouraging Book! | F87: Verified Purchase | H87: 5 | I87: This book is life-changing! I used a highlighter while reading it, because there were many things I wanted to easily refer back to. I need to buy a couple of copies for friends. I LOVED this book. | J87: Books and Stationary
A88: AH4LISFLHKWERFR7IGUXXFOFUWNA | B88: PROD087 | C88: Jean | D88: 45678.228 | E88: The book that will change your habits and results! | F88: Verified Purchase | G88: One | H88: 5 | I88: Atomic Habits is an amazing book guiding one to new ways of thinking about and planning habits to improve their lives. I started implementing the ideas as soon as I read the first chapter.James Clear makes it so easy to understand and make the changes necessary to improve habits for consistent results of improvement.Thank you Mr Clear for changing my life for the better! | J88: Books and Stationary
A89: AH5HOQ3UTZF5ZG2RHW5OJRL643YQ | B89: PROD088 | C89: Stephen H. A. Adams | D89: 45678.82 | E89: Clarity for a cluttered life | F89: Verified Purchase | H89: 5 | I89: Like so many others, I was taken by how clear the information in this book was imparted by James. I listened to it via audiobook, but felt impelled to buy a copy that I'd be able to refer back to in the coming years. I've already implemented several of the ideas in the book and have been able to clear a few bad habits while adding new good ones. | J89: Books and Stationary
A90: AHP4FYIEKSZRH4NPP2O27UF2A5FQ | B90: PROD089 | C90: Discreet Shopper | D90: 45679.038 | E90: Great book! | F90: Verified Purchase | H90: 5 | I90: This is my new favorite book! The writer packs a lot of thought and instruction in his book.The seller packaged and shipped the book promptly. | J90: Books and Stationary
A91: AHBAS5TNK4G2A7C56KJNZRIV6THQ | B91: PROD090 | C91: Valerie Daniel | D91: 45679.051 | E91: Read and Read Again | F91: Verified Purchase | H91: 5 | I91: I will have this Book on repeat each year! The concepts are worth the time investment! It will be part of my 1% better. | J91: Books and Stationary
A92: AETLSEK7GDFXXNYU4PQRKEMNTWRQ | B92: PROD091 | C92: Heena M | D92: 45679.176 | E92: Must read it | F92: Verified Purchase | H92: 5 | I92: A perfect book to change my life. Small small habits can be transforming our lives which learnt from this book. | J92: Books and Stationary
A93: AEJJVY6IOE55YRJZU6UODS5WCKRA | B93: PROD092 | C93: montgoti | D93: 45679.724 | E93: Playbook for those who have tried "cold turkey" or "crash diets" and failed. James has the formula! | F93: Verified Purchase | H93: 5 | I93: James lays out why we fail at "quick fixes", rely on "self-control", or accept defeat because we believe we are not disciplined enough. He explains in clear messages how small wins work with your health, wealth, and happiness just as compounding does with continued investments that are left to grow.Anyone who understands the process and makes even small commitments will benefit. | J93: Books and Stationary
A94: AHD7ZFWYAJPDUHLAEKLSKYBMBWKA | B94: PROD093 | C94: K.Victoria Smith | D94: 45679.795 | E94: A must read for anyone wanting to makes changes | F94: Verified Purchase | H94: 5 | I94: This is the most imortant book to read on how to understand habits. How we can create them or break them. It lays out why we all struggle with sticking to new habits and regress to the bad habits we want to break. Clear presents a simple strategy to improve our daily habits.It's working for me. Time to stack those habits. | J94: Books and Stationary
A95: AG3OIITA66NAX6JCGGCCLOPK25RQ | B95: PROD094 | C95: jchrisman | D95: 45680.09 | E95: This book changed the way I live. | F95: Verified Purchase | H95: 5 | I95: As a teacher, I use the steps to forming a habit in my classroom to build routines with students. I also use them to be a more efficient worker, athlete, mother, human. I quote this book too often, but the concepts are just so simple and easy to remember. James Clearâ€™s writing style is delightfully engaging, making the book a very enjoyable read. I was a little sad to finish it, but then I discovered his weekly newsletter! | J95: Books and Stationary
A96: AHW3DLIDTH7AFBYC7F6MHNKNGQ5Q | B96: PROD095 | C96: Jerry L. Funston | D96: 45680.201 | E96: Literally Life Changing | F96: Verified Purchase | H96: 5 | I96: I do not tend towards "Self-Help" books ... because most aren't helpful.Try harder, do more, etc ... these things don't work for me, but Clear's book offers practical, doable steps.And I love the explanations of why it works.â€œEvery action you take is a vote for the type of person you wish to become.â€ â€• James Clear | J96: Books and Stationary
A97: AHZY2RSYH7DDVD73Q22AULXK4PYA | B97: PROD096 | C97: Nesho Argueta | D97: 45680.496 | E97: Good book | F97: Verified Purchase | H97: 5 | I97: Good book, to creat habits, I created a habit that doesnt burden me, its read 15 mins a day (monday to friday) believe it or not, thats a book a month in some cases | J97: Books and Stationary
A98: AHWRFICKVK42RR2PXKUIJBOELYDQ | B98: PROD097 | C98: hrh | D98: 45680.713 | E98: Highly Recommend | F98: Verified Purchase | G98: 2 | H98: 5 | I98: donâ€™t read much anymore, but I make it a point to re-read Atomic Habits at least once a year, usually in January. The advice in the book is practical and easy to follow, especially for anyone looking to make positive changes in their life. Itâ€™s helped me build better habits and break some bad ones. Even though Iâ€™ve read it multiple times, I always find something new to take away from it. Highly recommend if youâ€™re looking to improve your daily routines. | J98: Books and Stationary
A99: AEJPYBYEMUFXVEDATTQG5V4EF5SQ | B99: PROD098 | C99: Aracely | D99: 45680.772 | E99: Helps reach goals | F99: Verified Purchase | H99: 5 | I99: This is the type of book you keep it around and read it more than once! | J99: Books and Stationary
A100: AF3MAAQAZ6AJTGYC736YEBTBD4HA | B100: PROD099 | C100: Apple | D100: 45680.864 | E100: Happy customer | F100: Verified Purchase | H100: 5 | I100: I love this book haven't read all soo far this book teaches you to have faith ðŸ™ this book was recommended by Crissy Carter and I also recommend it as well | J100: Books and Stationary
...

Sheet Data_cleaning
A1: User_id | B1: Product_ID | C1: rating | D1: date/timestamp | E1: category | F1: review | G1: Is_complete | H1: Valid_rating | I1: Rating_category | J1: Standardized user_id | K1: User Type | L1: Year | M1: Month | N1: Month name | O1: Quarter
A2: AH5M24Z73ZHQGN77WA3JT3Q7TEBQ | B2: PROD001 | C2: 5 | D2: 45658.158 | E2: kitchen | F2: NUWAVE, GRILL IS PRETTY GOOD SO FAR | G2: =IF(AND(A2<>"", B2<>"", C2<>"", D2<>"", E2<>"", F2<>""), "Complete", "Incomplete") -> Complete | H2: =IF(AND(C2>=1, C2<=5), "Valid", "Invalid") -> Valid | I2: =IF(C2>=4, "High(4-5)", IF(C2>=3, "Medium(3)", "Low(1-2)")) -> High(4-5) | J2: =TRIM(UPPER(A2)) -> AH5M24Z73ZHQGN77WA3JT3Q7TEBQ | K2: =IF(COUNTIF(Data_cleaning!$A:$A, A2)>10, "Power User", IF(COUNTIF(Data_cleaning!$A:$A, A2)>5, "Regular User", IF(COUNTIF(Data_cleaning!$A:$A, A2)>1, "Casual User", "One-Time User"))) -> One-Time User | L2: =YEAR(Table4[[#This Row],[date/timestamp]]) -> 2025 | M2: =MONTH(Table4[[#This Row],[date/timestamp]]) -> 1 | N2: =TEXT(Table4[[#This Row],[date/timestamp]], "MMMM") -> January | O2: ="Q"&INT((MONTH(D2)-1)/3)+1 -> Q1
A3: AFI7ALURI5CPDT4V7CUXZXLNFDVA | B3: PROD002 | C3: 5 | D3: 45658.222 | E3: kitchen | F3: Game changer | G3: =IF(AND(A3<>"", B3<>"", C3<>"", D3<>"", E3<>"", F3<>""), "Complete", "Incomplete") -> Complete | H3: =IF(AND(C3>=1, C3<=5), "Valid", "Invalid") -> Valid | I3: =IF(C3>=4, "High(4-5)", IF(C3>=3, "Medium(3)", "Low(1-2)")) -> High(4-5) | J3: =TRIM(UPPER(A3)) -> AFI7ALURI5CPDT4V7CUXZXLNFDVA | K3: =IF(COUNTIF(Data_cleaning!$A:$A, A3)>10, "Power User", IF(COUNTIF(Data_cleaning!$A:$A, A3)>5, "Regular User", IF(COUNTIF(Data_cleaning!$A:$A, A3)>1, "Casual User", "One-Time User"))) -> One-Time User | L3: =YEAR(Table4[[#This Row],[date/timestamp]]) -> 2025 | M3: =MONTH(Table4[[#This Row],[date/timestamp]]) -> 1 | N3: =TEXT(Table4[[#This Row],[date/timestamp]], "MMMM") -> January | O3: ="Q"&INT((MONTH(D3)-1)/3)+1 -> Q1
A4: AENH6LSB6BM7XLPEYUL43WBOD6JA | B4: PROD002 | C4: 4 | D4: 45658.447 | E4: kitchen | F4: More Than Meets My Needs | G4: =IF(AND(A4<>"", B4<>"", C4<>"", D4<>"", E4<>"", F4<>""), "Complete", "Incomplete") -> Complete | H4: =IF(AND(C4>=1, C4<=5), "Valid", "Invalid") -> Valid | I4: =IF(C4>=4, "High(4-5)", IF(C4>=3, "Medium(3)", "Low(1-2)")) -> High(4-5) | J4: =TRIM(UPPER(A4)) -> AENH6LSB6BM7XLPEYUL43WBOD6JA | K4: =IF(COUNTIF(Data_cleaning!$A:$A, A4)>10, "Power User", IF(COUNTIF(Data_cleaning!$A:$A, A4)>5, "Regular User", IF(COUNTIF(Data_cleaning!$A:$A, A4)>1, "Casual User", "One-Time User"))) -> One-Time User | L4: =YEAR(Table4[[#This Row],[date/timestamp]]) -> 2025 | M4: =MONTH(Table4[[#This Row],[date/timestamp]]) -> 1 | N4: =TEXT(Table4[[#This Row],[date/timestamp]], "MMMM") -> January | O4: ="Q"&INT((MONTH(D4)-1)/3)+1 -> Q1
A5: AHFAAT5CJ6IIGIURHFBICP44ZHVA | B5: PROD002 | C5: 5 | D5: 45658.657 | E5: kitchen | F5: Great machine and incredible customer support! | G5: =IF(AND(A5<>"", B5<>"", C5<>"", D5<>"", E5<>"", F5<>""), "Complete", "Incomplete") -> Complete | H5: =IF(AND(C5>=1, C5<=5), "Valid", "Invalid") -> Valid | I5: =IF(C5>=4, "High(4-5)", IF(C5>=3, "Medium(3)", "Low(1-2)")) -> High(4-5) | J5: =TRIM(UPPER(A5)) -> AHFAAT5CJ6IIGIURHFBICP44ZHVA | K5: =IF(COUNTIF(Data_cleaning!$A:$A, A5)>10, "Power User", IF(COUNTIF(Data_cleaning!$A:$A, A5)>5, "Regular User", IF(COUNTIF(Data_cleaning!$A:$A, A5)>1, "Casual User", "One-Time User"))) -> One-Time User | L5: =YEAR(Table4[[#This Row],[date/timestamp]]) -> 2025 | M5: =MONTH(Table4[[#This Row],[date/timestamp]]) -> 1 | N5: =TEXT(Table4[[#This Row],[date/timestamp]], "MMMM") -> January | O5: ="Q"&INT((MONTH(D5)-1)/3)+1 -> Q1
A6: AG4UMTWF2QN3BRDCSNVXTGZTPCAA | B6: PROD002 | C6: 5 | D6: 45658.837 | E6: kitchen | F6: Love it | G6: =IF(AND(A6<>"", B6<>"", C6<>"", D6<>"", E6<>"", F6<>""), "Complete", "Incomplete") -> Complete | H6: =IF(AND(C6>=1, C6<=5), "Valid", "Invalid") -> Valid | I6: =IF(C6>=4, "High(4-5)", IF(C6>=3, "Medium(3)", "Low(1-2)")) -> High(4-5) | J6: =TRIM(UPPER(A6)) -> AG4UMTWF2QN3BRDCSNVXTGZTPCAA | K6: =IF(COUNTIF(Data_cleaning!$A:$A, A6)>10, "Power User", IF(COUNTIF(Data_cleaning!$A:$A, A6)>5, "Regular User", IF(COUNTIF(Data_cleaning!$A:$A, A6)>1, "Casual User", "One-Time User"))) -> One-Time User | L6: =YEAR(Table4[[#This Row],[date/timestamp]]) -> 2025 | M6: =MONTH(Table4[[#This Row],[date/timestamp]]) -> 1 | N6: =TEXT(Table4[[#This Row],[date/timestamp]], "MMMM") -> January | O6: ="Q"&INT((MONTH(D6)-1)/3)+1 -> Q1
A7: AHO5TWX2UUDF22I2XOW4SZN2GDRQ | B7: PROD002 | C7: 5 | D7: 45658.996 | E7: kitchen | F7: Works great! | G7: =IF(AND(A7<>"", B7<>"", C7<>"", D7<>"", E7<>"", F7<>""), "Complete", "Incomplete") -> Complete | H7: =IF(AND(C7>=1, C7<=5), "Valid", "Invalid") -> Valid | I7: =IF(C7>=4, "High(4-5)", IF(C7>=3, "Medium(3)", "Low(1-2)")) -> High(4-5) | J7: =TRIM(UPPER(A7)) -> AHO5TWX2UUDF22I2XOW4SZN2GDRQ | K7: =IF(COUNTIF(Data_cleaning!$A:$A, A7)>10, "Power User", IF(COUNTIF(Data_cleaning!$A:$A, A7)>5, "Regular User", IF(COUNTIF(Data_cleaning!$A:$A, A7)>1, "Casual User", "One-Time User"))) -> One-Time User | L7: =YEAR(Table4[[#This Row],[date/timestamp]]) -> 2025 | M7: =MONTH(Table4[[#This Row],[date/timestamp]]) -> 1 | N7: =TEXT(Table4[[#This Row],[date/timestamp]], "MMMM") -> January | O7: ="Q"&INT((MONTH(D7)-1)/3)+1 -> Q1
A8: AFKZUIF6G6FKXDFO22NL5W3ZLHUQ | B8: PROD001 | C8: 5 | D8: 45659.039 | E8: kitchen | F8: Quiet! Hot! It has Rotisserie!! | G8: =IF(AND(A8<>"", B8<>"", C8<>"", D8<>"", E8<>"", F8<>""), "Complete", "Incomplete") -> Complete | H8: =IF(AND(C8>=1, C8<=5), "Valid", "Invalid") -> Valid | I8: =IF(C8>=4, "High(4-5)", IF(C8>=3, "Medium(3)", "Low(1-2)")) -> High(4-5) | J8: =TRIM(UPPER(A8)) -> AFKZUIF6G6FKXDFO22NL5W3ZLHUQ | K8: =IF(COUNTIF(Data_cleaning!$A:$A, A8)>10, "Power User", IF(COUNTIF(Data_cleaning!$A:$A, A8)>5, "Regular User", IF(COUNTIF(Data_cleaning!$A:$A, A8)>1, "Casual User", "One-Time User"))) -> One-Time User | L8: =YEAR(Table4[[#This Row],[date/timestamp]]) -> 2025 | M8: =MONTH(Table4[[#This Row],[date/timestamp]]) -> 1 | N8: =TEXT(Table4[[#This Row],[date/timestamp]], "MMMM") -> January | O8: ="Q"&INT((MONTH(D8)-1)/3)+1 -> Q1
A9: AF44IYYKVBHBUNKQEICMO4T7MJ6Q | B9: PROD001 | C9: 5 | D9: 45659.26 | E9: kitchen | F9: Good for cheese burgers | G9: =IF(AND(A9<>"", B9<>"", C9<>"", D9<>"", E9<>"", F9<>""), "Complete", "Incomplete") -> Complete | H9: =IF(AND(C9>=1, C9<=5), "Valid", "Invalid") -> Valid | I9: =IF(C9>=4, "High(4-5)", IF(C9>=3, "Medium(3)", "Low(1-2)")) -> High(4-5) | J9: =TRIM(UPPER(A9)) -> AF44IYYKVBHBUNKQEICMO4T7MJ6Q | K9: =IF(COUNTIF(Data_cleaning!$A:$A, A9)>10, "Power User", IF(COUNTIF(Data_cleaning!$A:$A, A9)>5, "Regular User", IF(COUNTIF(Data_cleaning!$A:$A, A9)>1, "Casual User", "One-Time User"))) -> One-Time User | L9: =YEAR(Table4[[#This Row],[date/timestamp]]) -> 2025 | M9: =MONTH(Table4[[#This Row],[date/timestamp]]) -> 1 | N9: =TEXT(Table4[[#This Row],[date/timestamp]], "MMMM") -> January | O9: ="Q"&INT((MONTH(D9)-1)/3)+1 -> Q1
A10: AGTVNHEOZCRUASEIU2QX6JBVWNCQ | B10: PROD002 | C10: 5 | D10: 45659.377 | E10: kitchen | F10: oven | G10: =IF(AND(A10<>"", B10<>"", C10<>"", D10<>"", E10<>"", F10<>""), "Complete", "Incomplete") -> Complete | H10: =IF(AND(C10>=1, C10<=5), "Valid", "Invalid") -> Valid | I10: =IF(C10>=4, "High(4-5)", IF(C10>=3, "Medium(3)", "Low(1-2)")) -> High(4-5) | J10: =TRIM(UPPER(A10)) -> AGTVNHEOZCRUASEIU2QX6JBVWNCQ | K10: =IF(COUNTIF(Data_cleaning!$A:$A, A10)>10, "Power User", IF(COUNTIF(Data_cleaning!$A:$A, A10)>5, "Regular User", IF(COUNTIF(Data_cleaning!$A:$A, A10)>1, "Casual User", "One-Time User"))) -> One-Time User | L10: =YEAR(Table4[[#This Row],[date/timestamp]]) -> 2025 | M10: =MONTH(Table4[[#This Row],[date/timestamp]]) -> 1 | N10: =TEXT(Table4[[#This Row],[date/timestamp]], "MMMM") -> January | O10: ="Q"&INT((MONTH(D10)-1)/3)+1 -> Q1
A11: AEZMHCTOR4XWPQJJEP47UBY2G4UA | B11: PROD010 | C11: 4 | D11: 45660.153 | E11: kitchen | F11: Good | G11: =IF(AND(A11<>"", B11<>"", C11<>"", D11<>"", E11<>"", F11<>""), "Complete", "Incomplete") -> Complete | H11: =IF(AND(C11>=1, C11<=5), "Valid", "Invalid") -> Valid | I11: =IF(C11>=4, "High(4-5)", IF(C11>=3, "Medium(3)", "Low(1-2)")) -> High(4-5) | J11: =TRIM(UPPER(A11)) -> AEZMHCTOR4XWPQJJEP47UBY2G4UA | K11: =IF(COUNTIF(Data_cleaning!$A:$A, A11)>10, "Power User", IF(COUNTIF(Data_cleaning!$A:$A, A11)>5, "Regular User", IF(COUNTIF(Data_cleaning!$A:$A, A11)>1, "Casual User", "One-Time User"))) -> One-Time User | L11: =YEAR(Table4[[#This Row],[date/timestamp]]) -> 2025 | M11: =MONTH(Table4[[#This Row],[date/timestamp]]) -> 1 | N11: =TEXT(Table4[[#This Row],[date/timestamp]], "MMMM") -> January | O11: ="Q"&INT((MONTH(D11)-1)/3)+1 -> Q1
A12: AFGOHTTJWRAYHJQKZZULDJID5ADQ | B12: PROD011 | C12: 5 | D12: 45660.29 | E12: Electronics | F12: Great tool for busy mom | G12: =IF(AND(A12<>"", B12<>"", C12<>"", D12<>"", E12<>"", F12<>""), "Complete", "Incomplete") -> Complete | H12: =IF(AND(C12>=1, C12<=5), "Valid", "Invalid") -> Valid | I12: =IF(C12>=4, "High(4-5)", IF(C12>=3, "Medium(3)", "Low(1-2)")) -> High(4-5) | J12: =TRIM(UPPER(A12)) -> AFGOHTTJWRAYHJQKZZULDJID5ADQ | K12: =IF(COUNTIF(Data_cleaning!$A:$A, A12)>10, "Power User", IF(COUNTIF(Data_cleaning!$A:$A, A12)>5, "Regular User", IF(COUNTIF(Data_cleaning!$A:$A, A12)>1, "Casual User", "One-Time User"))) -> One-Time User | L12: =YEAR(Table4[[#This Row],[date/timestamp]]) -> 2025 | M12: =MONTH(Table4[[#This Row],[date/timestamp]]) -> 1 | N12: =TEXT(Table4[[#This Row],[date/timestamp]], "MMMM") -> January | O12: ="Q"&INT((MONTH(D12)-1)/3)+1 -> Q1
A13: AFFUJJPQEWVDXYGSKC3SLMIIU75Q | B13: PROD012 | C13: 5 | D13: 45660.524 | E13: Electronics | F13: Amazing, my favorite purchase | G13: =IF(AND(A13<>"", B13<>"", C13<>"", D13<>"", E13<>"", F13<>""), "Complete", "Incomplete") -> Complete | H13: =IF(AND(C13>=1, C13<=5), "Valid", "Invalid") -> Valid | I13: =IF(C13>=4, "High(4-5)", IF(C13>=3, "Medium(3)", "Low(1-2)")) -> High(4-5) | J13: =TRIM(UPPER(A13)) -> AFFUJJPQEWVDXYGSKC3SLMIIU75Q | K13: =IF(COUNTIF(Data_cleaning!$A:$A, A13)>10, "Power User", IF(COUNTIF(Data_cleaning!$A:$A, A13)>5, "Regular User", IF(COUNTIF(Data_cleaning!$A:$A, A13)>1, "Casual User", "One-Time User"))) -> One-Time User | L13: =YEAR(Table4[[#This Row],[date/timestamp]]) -> 2025 | M13: =MONTH(Table4[[#This Row],[date/timestamp]]) -> 1 | N13: =TEXT(Table4[[#This Row],[date/timestamp]], "MMMM") -> January | O13: ="Q"&INT((MONTH(D13)-1)/3)+1 -> Q1
... A1444: AE5KYF2QVH6VMX4F4FAZS57E2FXQ | B1444: PROD1497 | C1444: 5 | D1444: 45967.847 | E1444: Cloth and accessaries | F1444: Un poco liviana, pero parece buena. | G1444: =IF(AND(A1444<>"", B1444<>"", C1444<>"", D1444<>"", E1444<>"", F1444<>""), "Complete", "Incomplete") -> Complete | H1444: =IF(AND(C1444>=1, C1444<=5), "Valid", "Invalid") -> Valid | I1444: =IF(C1444>=4, "High(4-5)", IF(C1444>=3, "Medium(3)", "Low(1-2)")) -> High(4-5) | J1444: =TRIM(UPPER(A1444)) -> AE5KYF2QVH6VMX4F4FAZS57E2FXQ | K1444: =IF(COUNTIF(Data_cleaning!$A:$A, A1444)>10, "Power User", IF(COUNTIF(Data_cleaning!$A:$A, A1444)>5, "Regular User", IF(COUNTIF(Data_cleaning!$A:$A, A1444)>1, "Casual User", "One-Time User"))) -> One-Time User | L1444: =YEAR(Table4[[#This Row],[date/timestamp]]) -> 2025 | M1444: =MONTH(Table4[[#This Row],[date/timestamp]]) -> 11 | N1444: =TEXT(Table4[[#This Row],[date/timestamp]], "MMMM") -> November | O1444: ="Q"&INT((MONTH(D1444)-1)/3)+1 -> Q4

Sheet Analysis
A1: OVERALL STATISTICS | E1: TOP ACTIVE USERS | I1: COUNT BY SEGMENT | L1: REVIEWS OVERTIME
A2: Metric | B2: Formula | C2: Result | E2: User id | F2: {=INDEX(Data_cleaning!A2:A1500,MATCH(MAX(COUNTIF(Data_cleaning!A2:A1500,Data_cleaning!A2:A1500)),COUNTIF(Data_cleaning!A2:A1500,Data_cleaning!A2:A1500),0))} -> AECDXBV7YXUT7T2XYKIOTAMMFBKA | I2: Power users | J2: =COUNTIF(Data_cleaning!K:K, "Power User") -> 0 | L2: Row Labels | M2: Count of User_id | O2: GROWTH RATE
A3: Total reviews | B3: =COUNTA(Data_cleaning! A:A)-1' | C3: =COUNTA(Data_cleaning!A:A)-1 -> 1443 | E3: Review count | F3: =COUNTIF(Data_cleaning!A:A, A616) -> 1 | I3: Regular users | J3: =COUNTIF(Data_cleaning!K:K, "Regular User") -> 0 | L3: 2025 | O3: 0
A4: Total users | B4: =SUMPRODUCT(1/COUNTIF(Data_Cleaning!A:A,Data_Cleaning!A:A))` | C4: =SUMPRODUCT((Data_cleaning!A2:A1444<>"")/COUNTIF(Data_cleaning!A2:A1444,Data_cleaning!A2:A1444&"")) -> 1420 | I4: Casual users | J4: =COUNTIF(Data_cleaning!K:K, "Casual User") -> 46 | L4: 1 | M4: 141 | O4: =GETPIVOTDATA("User_id",$L$2,"Year",2025,"Month",2)-GETPIVOTDATA("User_id",$L$2,"Year",2025,"Month",1)/GETPIVOTDATA("User_id",$L$2,"Year",2025,"Month",1) -> 124
A5: Total products | B5: =SUMPRODUCT(/COUNTIF(Data_Cleaning!B:B,Data_Cleaning!B:B))` | C5: =SUMPRODUCT((Data_cleaning!B2:B1444<>"")/COUNTIF(Data_cleaning!B2:B1444,Data_cleaning!B2:B1444&"")) -> 1406 | I5: One time users | J5: =COUNTIF(Data_cleaning!K:K, "One-Time User") -> 1397 | L5: 2 | M5: 125 | O5: =GETPIVOTDATA("User_id",$L$2,"Year",2025,"Month",3)-GETPIVOTDATA("User_id",$L$2,"Year",2025,"Month",2)/GETPIVOTDATA("User_id",$L$2,"Year",2025,"Month",2) -> 142
A6: Average rating | B6: `=AVERAGE(Data_Cleaning!C:C)` | C6: =ROUND(AVERAGE(Data_cleaning!C:C), 2) -> 4.56 | L6: 3 | M6: 143 | O6: =GETPIVOTDATA("User_id",$L$2,"Year",2025,"Month",4)-GETPIVOTDATA("User_id",$L$2,"Year",2025,"Month",3)/GETPIVOTDATA("User_id",$L$2,"Year",2025,"Month",3) -> 149
A7: Rating standard deviation | B7: `=STDEV.P(Data_Cleaning!C:C)` | C7: =ROUND(_xlfn.STDEV.P(Data_cleaning!C:C), 2) -> 0.79 | E7: overall average rating: | L7: 4 | M7: 150 | O7: =GETPIVOTDATA("User_id",$L$2,"Year",2025,"Month",5)-GETPIVOTDATA("User_id",$L$2,"Year",2025,"Month",4)/GETPIVOTDATA("User_id",$L$2,"Year",2025,"Month",4) -> 100
E8: =ROUND(AVERAGE(Data_cleaning!C2:C1500), 2) -> 4.56 | L8: 5 | M8: 101 | O8: =GETPIVOTDATA("User_id",$L$2,"Year",2025,"Month",6)-GETPIVOTDATA("User_id",$L$2,"Year",2025,"Month",5)/GETPIVOTDATA("User_id",$L$2,"Year",2025,"Month",5) -> 154
L9: 6 | M9: 155 | O9: =GETPIVOTDATA("User_id",$L$2,"Year",2025,"Month",7)-GETPIVOTDATA("User_id",$L$2,"Year",2025,"Month",6)/GETPIVOTDATA("User_id",$L$2,"Year",2025,"Month",6) -> 140
L10: 7 | M10: 141 | O10: =GETPIVOTDATA("User_id",$L$2,"Year",2025,"Month",8)-GETPIVOTDATA("User_id",$L$2,"Year",2025,"Month",7)/GETPIVOTDATA("User_id",$L$2,"Year",2025,"Month",7) -> 151
A11: USER BEHAVIOUR ANALYSIS | D11: PRODUCT POPULARITY | H11: RATING DISTRIBUTION ANALYSIS | L11: 8 | M11: 152 | O11: =GETPIVOTDATA("User_id",$L$2,"Year",2025,"Month",9)-GETPIVOTDATA("User_id",$L$2,"Year",2025,"Month",8)/GETPIVOTDATA("User_id",$L$2,"Year",2025,"Month",8) -> 157
A12: Row Labels | B12: Count of Product_ID | D12: Row Labels | E12: Average of rating | F12: Count of rating2 | H12: Rating | I12: Count | J12: Percentage | L12: 9 | M12: 158 | O12: =GETPIVOTDATA("User_id",$L$2,"Year",2025,"Month",10)-GETPIVOTDATA("User_id",$L$2,"Year",2025,"Month",9)/GETPIVOTDATA("User_id",$L$2,"Year",2025,"Month",9) -> 150
A13: AHZOS45H5WKR7B2PWESHKQFB75SQ | B13: 2 | D13: PROD110 | E13: 5 | F13: 6 | H13: 5 stars | I13: =COUNTIF(Data_cleaning!C:C, 5) -> 994 | J13: =ROUND(I13/I18, 2) -> 0.69 | L13: 10 | M13: 151 | O13: =GETPIVOTDATA("User_id",$L$2,"Year",2025,"Month",11)-GETPIVOTDATA("User_id",$L$2,"Year",2025,"Month",10)/GETPIVOTDATA("User_id",$L$2,"Year",2025,"Month",11) -> 20.192308
A14: AHXONVJXS6KFLSBYAWMQYAB5P6JQ | B14: 2 | D14: PROD002 | E14: 4.8333333 | F14: 6 | H14: 4 stars | I14: =COUNTIF(Data_cleaning!C:C, 4) -> 325 | J14: =ROUND(I14/I18, 2) -> 0.23 | L14: 11 | M14: 26
A15: AHUV6JS3SNZFQNQFXUDKBA72DNSQ | B15: 2 | D15: PROD010 | E15: 4.7142857 | F15: 7 | H15: 3 stars | I15: =COUNTIF(Data_cleaning!C:C, 3) -> 84 | J15: =ROUND(I15/I18, 2) -> 0.06 | L15: Grand Total | M15: 1443
A16: AHG5QM4MKOFCXJWVDVWNLF42S2WQ | B16: 2 | D16: PROD1477 | E16: 4.5714286 | F16: 7 | H16: 2 stars | I16: =COUNTIF(Data_cleaning!C:C, 2) -> 17 | J16: =ROUND(I16/I18, 2) -> 0.01
A17: AHJ64Z5RDZCOUICREXSICDIUMROA | B17: 2 | D17: PROD012 | E17: 4.5 | F17: 6 | H17: 1 star | I17: =COUNTIF(Data_cleaning!C:C, 1) -> 23 | J17: =ROUND(I17/I18, 2) -> 0.02
A18: AHJMUF7CPNEJZZUXVCAK7KQRHI6A | B18: 2 | D18: Grand Total | E18: 4.71875 | F18: 32 | H18: TOTAL | I18: =SUM(I13,I14,I15,I16,I17) -> 1443
A19: AGRFRPTYNXGE3CGAIO7ZENQBUZWA | B19: 2
A20: AGEOPVR2EZFXK4VKO4J5AE6LORIA | B20: 2 | L20: AVERAGE RATING TREND
A21: AGTSK6Q7WW6L57XNLK74RFMLIMDA | B21: 2 | L21: Row Labels | M21: Average of rating
A22: AG5VTTQKNBBVOCRRFD7SUISNIEOQ | B22: 2 | D22: MOST REVIWED PRODUCTS | L22: 2025 | M22: 4.5592516
A23: AGLZY6EFUHINYSW7LPU7HNWBFIXA | B23: 2 | D23: Product_id | E23: {=INDEX(Data_cleaning!B2:B1500, MATCH(MAX(COUNTIF(Data_cleaning!B2:B1500, Data_cleaning!B2:B1500)), COUNTIF(Data_cleaning!B2:B1500, Data_cleaning!B2:B1500), 0))} -> PROD010 | F23: {=INDEX(Data_cleaning!B1413:B1444, MATCH(MAX(COUNTIF(Data_cleaning!B1413:B1444, Data_cleaning!B1413:B1444)), COUNTIF(Data_cleaning!B1413:B1444, Data_cleaning!B1413:B1444), 0))} -> PROD1477 | G23: {=INDEX(Data_cleaning!B13:B46, MATCH(MAX(COUNTIF(Data_cleaning!B13:B46, Data_cleaning!B13:B46)), COUNTIF(Data_cleaning!B13:B46, Data_cleaning!B13:B46), 0))} -> PROD012 | H23: {=INDEX(Data_cleaning!B111:B116, MATCH(MAX(COUNTIF(Data_cleaning!B111:B116, Data_cleaning!B111:B116)), COUNTIF(Data_cleaning!B111:B116, Data_cleaning!B111:B116), 0))} -> PROD110 | L23: Q1 | M23: 4.6381418
A24: AF62RCQHBHLR7RTVQ3RXW7PFZAUA | B24: 2 | D24: Review count | E24: =COUNTIF(Data_cleaning!B:B, Analysis!E23) -> 7 | F24: =COUNTIF(Data_cleaning!B:B, Analysis!F23) -> 7 | G24: =COUNTIF(Data_cleaning!B:B, Analysis!G23) -> 6 | H24: =COUNTIF(Data_cleaning!B:B, Analysis!H23) -> 6 | L24: Q2 | M24: 4.4729064
A25: AFLO7QKN3WVVES5ASJ5PBDHMKZLQ | B25: 2 | D25: Average rating | E25: =ROUND(AVERAGEIF(Data_cleaning!B:B, E23, Data_cleaning!C:C), 2) -> 4.71 | F25: =ROUND(AVERAGEIF(Data_cleaning!B:B, F23, Data_cleaning!C:C), 2) -> 4.57 | G25: =ROUND(AVERAGEIF(Data_cleaning!B:B, G23, Data_cleaning!C:C), 2) -> 4.5 | H25: =ROUND(AVERAGEIF(Data_cleaning!B:B, H23, Data_cleaning!C:C), 2) -> 5 | L25: Q3 | M25: 4.5831486
A26: AFJAP2RUXWCRIF356GGACRNQLFBA | B26: 2 | L26: Q4 | M26: 4.5141243
A27: AET6PNHHRUU54WP4OFZHYAU7KBKA | B27: 2 | D27: RATING BIAS ANALYSIS | L27: Grand Total | M27: 4.5592516
A28: AEGUBOG4HFKND2TYI7FMSJRCLYRQ | B28: 2 | D28: Positive bias (4-5) | E28: =ROUND(COUNTIFS(Data_cleaning!C:C, ">=4")/ COUNTA(Data_cleaning!C:C), 2) -> 0.91
A29: AEGI7HRSGXLKABXRNEZXHRSFIHKA | B29: 2 | D29: Negative bias (1-2) | E29: =ROUND(COUNTIFS(Data_cleaning!C:C, "<=2")/ COUNTA(Data_cleaning!C:C), 2) -> 0.03
A30: AE3PNVS6M2VT2ULP6PAYISVOKXAQ | B30: 2
A31: AEIWLJG5KA6GRV66IRCCGUEUP73A | B31: 2
A32: AECDXBV7YXUT7T2XYKIOTAMMFBKA | B32: 2 | D32: PRODUCT CO-OCCURRENCE
A33: AEUJ53NKXU75BT6LVFDQSOAZIJBQ | B33: 2 | D33: =SUMPRODUCT((Data_cleaning!$A:$A=Data_cleaning!A3)*(Data_cleaning!$B:$B=Data_cleaning!B3)*(Data_cleaning!$B:$B=Data_cleaning!B4)) -> 1
A34: AEFVTTFB7NFHCAZVLUULL3YC7WMA | B34: 2
A35: AF2BLE54TEMGZ546U763ZHZRXC4A | B35: 2
A36: AHRQQN36UWBMDXA7G53775PYRJRQ | B36: 1
A37: AHMUR6CSCHC2PA6YHLQL6TGCZKUA | B37: 1
A38: AH4IYTPAALBRN5P2U7NE3JBB6TRQ | B38: 1
A39: AH4L6S323U6DZDT2NF6KJJRRSVLQ | B39: 1
A40: AHP7T6TYPYEITN3VY5EVZQKIVS2A | B40: 1
A41: AH4LISFLHKWERFR7IGUXXFOFUWNA | B41: 1
A42: AHUR3BFNMT42I6C6KHC2N5ZHH6PQ | B42: 1
A43: AH4MRI6EUYRQY2OV4P3C6CDLK2MA | B43: 1
A44: AHLKACHCST4JG3ET5D5J7NEHSYUQ | B44: 1
A45: AH4OZ5CUSNMTEOK6E4CC4F4OSSRQ | B45: 1
... A1432: AEJTBLFJETHBK7OOIQFVFF3RQUIQ | B1432: 1
A1433: (blank)
A1434: Grand Total | B1434: 1443

Sheet Dashboard
A1: USER REVIEW AND ENGAGEMENT ANALYSIS DASHBOARD
A3: Total Reviews | B3: Active Users | C3: Products Rated | D3: Avg Rating
A4: =COUNTA(Data_cleaning!A:A)-1 -> 1443 | B4: =SUMPRODUCT((Data_cleaning!A2:A1444<>"")/COUNTIF(Data_cleaning!A2:A1444,Data_cleaning!A2:A1444&"")) -> 1420 | C4: =SUMPRODUCT((Data_cleaning!B2:B1444<>"")/COUNTIF(Data_cleaning!B2:B1444,Data_cleaning!B2:B1444&"")) -> 1406 | D4: =TEXT(AVERAGE(Data_cleaning!C2:C1444),"0.0")&" ⭐" -> 4.6 ⭐
A33: Most Reviewed Products
A34: Product_id | B34: Avg rating | C34: Review count | D34: Recommendation
A35: PROD010 | B35: 4.71 | C35: 7 | D35: =IF(AND(B35>=4, C35>=5), "Recommended", "") -> Recommended
A36: PROD1477 | B36: 4.57 | C36: 7 | D36: =IF(AND(B36>=4, C36>=5), "Recommended", "") -> Recommended
A37: PROD012 | B37: 4.5 | C37: 6 | D37: =IF(AND(B37>=4, C37>=5), "Recommended", "") -> Recommended
A38: PROD110 | B38: 5 | C38: 6 | D38: =IF(AND(B38>=4, C38>=5), "Recommended", "") -> Recommended
A41: INSIGHTS
A42: {="The average rating is " & TEXT(AVERAGE(Data_cleaning!C:C),"0.00") & CHAR(10) & "with " & TEXT(COUNTIFS(Data_cleaning!C:C,">=4")/COUNTA(Data_cleaning!C:C),"0%") & " of reviews being 4+ stars, indicating positive user sentiment."} -> The average rating is 4.56 with 91% of reviews being 4+ stars, indicating positive user sentiment.
A43: Power users contribute 0% of all the reviews
A44: 46 casual users contribute 3% of all the reviews
A45: 1397 one-time users contribute 97% of all the reviews

Sheet Documentation
A1: PROJECT DOCUMENATION
A3: Project Overview
A4: Project Title: | B4: User Review and Engagement Analysis
A5: Created by: | B5: Akinyemi Aminat
A6: Date: | B6: 45911
A7: Dataset source: | B7: https://cseweb.ucsd.edu/jmcauley/datasets.html
A8: Data size | B8: =Analysis!C3&" reviews" -> 1443 reviews
A9: Tools used | B9: Microsoft Excel
A12: Data Dictionary
A13: Column name | B13: Description | C13: Data type | D13: Example
A14: User_id | B14: Unique user identifier | C14: Text | D14: userwerts
A15: Product_id | B15: unique product identifier | C15: Text | D15: PROD112
A16: Rating | B16: User rating | C16: Number | D16: 4
A17: Date | B17: Review date | C17: Date | D17: 45658
A18: Month | B18: Extracted year | C18: Number | D18: 3
A19: Year | B19: extracted month | C19: Number | D19: 2024
A20: Month name | B20: month name | C20: Text | D20: January
A21: Rating category | B21: rating category | C21: Text | D21: High
A22: Quarter | B22: quarter of the year | C22: Text | D22: Q1
A23: Review | B23: User comment | C23: Text | D23: very good
A25: Workbook structure
A26: Raw_data | B26: Original dataset
A27: Data_cleaning | B27: cleaned dataset with extra columns for analysis
A28: Analysis | B28: calculations, pivot tables, and statistical analysis.
A29: Dashboard | B29: Visual presentation with charts and metrics
A30: Documentation | B30: project notes
A32: KEY FINDINGS
A33: Rating pattern:
A34: Average rating across all products is 4.56 stars
A35: 0.91% of the reviews are positive
A36: 0.03% of the reviews are negative
A37: The most common rating is 5 stars
A38: the least common rating is 1 star
A40: User Behaviour:
A41: The total unique users: 1443
A42: power users contribute 0% of all the ratings
A43: Casual users contribute 3% of all the ratings
A44: One-time users contribute 97% of all the ratings
... A50: Four products meet the criteria 4+ stars and 5+ reviews
